{
  "__data_type": "UTC ",
  "Appearance_Type": {
    "type": "word",
    "value": 278
  },
  "BodyBag": {
    "type": "byte",
    "value": 0
  },
  "Cha": {
    "type": "byte",
    "value": 10
  },
  "ChallengeRating": {
    "type": "float",
    "value": 2.0
  },
  "ClassList": {
    "type": "list",
    "value": [
      {
        "__struct_id": 2,
        "Class": {
          "type": "int",
          "value": 4
        },
        "ClassLevel": {
          "type": "short",
          "value": 1
        }
      },
      {
        "__struct_id": 2,
        "Class": {
          "type": "int",
          "value": 8
        },
        "ClassLevel": {
          "type": "short",
          "value": 1
        }
      }
    ]
  },
  "Comment": {
    "type": "cexostring",
    "value": ""
  },
  "Con": {
    "type": "byte",
    "value": 11
  },
  "Conversation": {
    "type": "resref",
    "value": ""
  },
  "CRAdjust": {
    "type": "int",
    "value": 0
  },
  "CurrentHitPoints": {
    "type": "short",
    "value": 16
  },
  "DecayTime": {
    "type": "dword",
    "value": 300000
  },
  "Deity": {
    "type": "cexostring",
    "value": ""
  },
  "Description": {
    "id": 57343,
    "type": "cexolocstring",
    "value": {
      "0": "This man looks haggard and ready to fight. He's obviously not friendly."
    }
  },
  "Dex": {
    "type": "byte",
    "value": 11
  },
  "Disarmable": {
    "type": "byte",
    "value": 1
  },
  "Equip_ItemList": {
    "type": "list",
    "value": [
      {
        "__struct_id": 2,
        "EquippedRes": {
          "type": "resref",
          "value": "nw_aarcl002"
        }
      }
    ]
  },
  "FactionID": {
    "type": "word",
    "value": 6
  },
  "FeatList": {
    "type": "list",
    "value": [
      {
        "__struct_id": 1,
        "Feat": {
          "type": "word",
          "value": 2
        }
      },
      {
        "__struct_id": 1,
        "Feat": {
          "type": "word",
          "value": 3
        }
      },
      {
        "__struct_id": 1,
        "Feat": {
          "type": "word",
          "value": 4
        }
      },
      {
        "__struct_id": 1,
        "Feat": {
          "type": "word",
          "value": 206
        }
      },
      {
        "__struct_id": 1,
        "Feat": {
          "type": "word",
          "value": 32
        }
      },
      {
        "__struct_id": 1,
        "Feat": {
          "type": "word",
          "value": 221
        }
      },
      {
        "__struct_id": 1,
        "Feat": {
          "type": "word",
          "value": 45
        }
      },
      {
        "__struct_id": 1,
        "Feat": {
          "type": "word",
          "value": 46
        }
      }
    ]
  },
  "FirstName": {
    "id": 24586,
    "type": "cexolocstring",
    "value": {
      "0": "Thug"
    }
  },
  "fortbonus": {
    "type": "short",
    "value": 0
  },
  "Gender": {
    "type": "byte",
    "value": 0
  },
  "GoodEvil": {
    "type": "byte",
    "value": 0
  },
  "HitPoints": {
    "type": "short",
    "value": 16
  },
  "Int": {
    "type": "byte",
    "value": 10
  },
  "Interruptable": {
    "type": "byte",
    "value": 1
  },
  "IsImmortal": {
    "type": "byte",
    "value": 0
  },
  "IsPC": {
    "type": "byte",
    "value": 0
  },
  "LastName": {
    "type": "cexolocstring",
    "value": {}
  },
  "LawfulChaotic": {
    "type": "byte",
    "value": 0
  },
  "Lootable": {
    "type": "byte",
    "value": 0
  },
  "MaxHitPoints": {
    "type": "short",
    "value": 16
  },
  "NaturalAC": {
    "type": "byte",
    "value": 0
  },
  "NoPermDeath": {
    "type": "byte",
    "value": 0
  },
  "PaletteID": {
    "type": "byte",
    "value": 38
  },
  "PerceptionRange": {
    "type": "byte",
    "value": 11
  },
  "Phenotype": {
    "type": "int",
    "value": 0
  },
  "Plot": {
    "type": "byte",
    "value": 0
  },
  "PortraitId": {
    "type": "word",
    "value": 108
  },
  "Race": {
    "type": "byte",
    "value": 6
  },
  "refbonus": {
    "type": "short",
    "value": 0
  },
  "ScriptAttacked": {
    "type": "resref",
    "value": "ai_onattacked"
  },
  "ScriptDamaged": {
    "type": "resref",
    "value": "ai_ondamaged"
  },
  "ScriptDeath": {
    "type": "resref",
    "value": "ai_ondeath"
  },
  "ScriptDialogue": {
    "type": "resref",
    "value": "ai_onconverse"
  },
  "ScriptDisturbed": {
    "type": "resref",
    "value": "ai_ondisturb"
  },
  "ScriptEndRound": {
    "type": "resref",
    "value": "ai_oncombrnd"
  },
  "ScriptHeartbeat": {
    "type": "resref",
    "value": "ai_onheartb"
  },
  "ScriptOnBlocked": {
    "type": "resref",
    "value": "ai_onblocked"
  },
  "ScriptOnNotice": {
    "type": "resref",
    "value": "ai_onpercep"
  },
  "ScriptRested": {
    "type": "resref",
    "value": "ai_onrest"
  },
  "ScriptSpawn": {
    "type": "resref",
    "value": "ai_onspawn"
  },
  "ScriptSpellAt": {
    "type": "resref",
    "value": "ai_onspellcast"
  },
  "ScriptUserDefine": {
    "type": "resref",
    "value": "ai_onuserdef"
  },
  "SkillList": {
    "type": "list",
    "value": [
      {
        "__struct_id": 0,
        "Rank": {
          "type": "byte",
          "value": 0
        }
      },
      {
        "__struct_id": 0,
        "Rank": {
          "type": "byte",
          "value": 0
        }
      },
      {
        "__struct_id": 0,
        "Rank": {
          "type": "byte",
          "value": 0
        }
      },
      {
        "__struct_id": 0,
        "Rank": {
          "type": "byte",
          "value": 6
        }
      },
      {
        "__struct_id": 0,
        "Rank": {
          "type": "byte",
          "value": 0
        }
      },
      {
        "__struct_id": 0,
        "Rank": {
          "type": "byte",
          "value": 0
        }
      },
      {
        "__struct_id": 0,
        "Rank": {
          "type": "byte",
          "value": 6
        }
      },
      {
        "__struct_id": 0,
        "Rank": {
          "type": "byte",
          "value": 0
        }
      },
      {
        "__struct_id": 0,
        "Rank": {
          "type": "byte",
          "value": 0
        }
      },
      {
        "__struct_id": 0,
        "Rank": {
          "type": "byte",
          "value": 0
        }
      },
      {
        "__struct_id": 0,
        "Rank": {
          "type": "byte",
          "value": 0
        }
      },
      {
        "__struct_id": 0,
        "Rank": {
          "type": "byte",
          "value": 0
        }
      },
      {
        "__struct_id": 0,
        "Rank": {
          "type": "byte",
          "value": 0
        }
      },
      {
        "__struct_id": 0,
        "Rank": {
          "type": "byte",
          "value": 0
        }
      },
      {
        "__struct_id": 0,
        "Rank": {
          "type": "byte",
          "value": 0
        }
      },
      {
        "__struct_id": 0,
        "Rank": {
          "type": "byte",
          "value": 0
        }
      },
      {
        "__struct_id": 0,
        "Rank": {
          "type": "byte",
          "value": 0
        }
      },
      {
        "__struct_id": 0,
        "Rank": {
          "type": "byte",
          "value": 6
        }
      },
      {
        "__struct_id": 0,
        "Rank": {
          "type": "byte",
          "value": 0
        }
      },
      {
        "__struct_id": 0,
        "Rank": {
          "type": "byte",
          "value": 0
        }
      },
      {
        "__struct_id": 0,
        "Rank": {
          "type": "byte",
          "value": 0
        }
      },
      {
        "__struct_id": 0,
        "Rank": {
          "type": "byte",
          "value": 6
        }
      },
      {
        "__struct_id": 0,
        "Rank": {
          "type": "byte",
          "value": 0
        }
      },
      {
        "__struct_id": 0,
        "Rank": {
          "type": "byte",
          "value": 0
        }
      },
      {
        "__struct_id": 0,
        "Rank": {
          "type": "byte",
          "value": 0
        }
      },
      {
        "__struct_id": 0,
        "Rank": {
          "type": "byte",
          "value": 0
        }
      },
      {
        "__struct_id": 0,
        "Rank": {
          "type": "byte",
          "value": 0
        }
      },
      {
        "__struct_id": 0,
        "Rank": {
          "type": "byte",
          "value": 0
        }
      }
    ]
  },
  "SoundSetFile": {
    "type": "word",
    "value": 147
  },
  "SpecAbilityList": {
    "type": "list",
    "value": []
  },
  "StartingPackage": {
    "type": "byte",
    "value": 4
  },
  "Str": {
    "type": "byte",
    "value": 10
  },
  "Subrace": {
    "type": "cexostring",
    "value": ""
  },
  "Tag": {
    "type": "cexostring",
    "value": ""
  },
  "Tail_New": {
    "type": "dword",
    "value": 0
  },
  "TemplateList": {
    "type": "list",
    "value": []
  },
  "TemplateResRef": {
    "type": "resref",
    "value": "thug"
  },
  "VarTable": {
    "type": "list",
    "value": [
      {
        "__struct_id": 0,
        "Name": {
          "type": "cexostring",
          "value": "spawn_script"
        },
        "Type": {
          "type": "dword",
          "value": 3
        },
        "Value": {
          "type": "cexostring",
          "value": "rand_sewerthug"
        }
      }
    ]
  },
  "WalkRate": {
    "type": "int",
    "value": 7
  },
  "willbonus": {
    "type": "short",
    "value": 0
  },
  "Wings_New": {
    "type": "dword",
    "value": 0
  },
  "Wis": {
    "type": "byte",
    "value": 11
  }
}
