{
  "__data_type": "UTC ",
  "Appearance_Type": {
    "type": "word",
    "value": 198
  },
  "BodyBag": {
    "type": "byte",
    "value": 0
  },
  "Cha": {
    "type": "byte",
    "value": 3
  },
  "ChallengeRating": {
    "type": "float",
    "value": 1.0
  },
  "ClassList": {
    "type": "list",
    "value": [
      {
        "__struct_id": 2,
        "Class": {
          "type": "int",
          "value": 19
        },
        "ClassLevel": {
          "type": "short",
          "value": 2
        }
      }
    ]
  },
  "Comment": {
    "type": "cexostring",
    "value": ""
  },
  "Con": {
    "type": "byte",
    "value": 12
  },
  "Conversation": {
    "type": "resref",
    "value": ""
  },
  "CRAdjust": {
    "type": "int",
    "value": 0
  },
  "CurrentHitPoints": {
    "type": "short",
    "value": 16
  },
  "DecayTime": {
    "type": "dword",
    "value": 300000
  },
  "Deity": {
    "type": "cexostring",
    "value": ""
  },
  "Description": {
    "id": 12826,
    "type": "cexolocstring",
    "value": {}
  },
  "Dex": {
    "type": "byte",
    "value": 6
  },
  "Disarmable": {
    "type": "byte",
    "value": 0
  },
  "Equip_ItemList": {
    "type": "list",
    "value": [
      {
        "__struct_id": 65536,
        "EquippedRes": {
          "type": "resref",
          "value": "cre_zomslam"
        }
      },
      {
        "__struct_id": 131072,
        "EquippedRes": {
          "type": "resref",
          "value": "nw_it_creitemunf"
        }
      }
    ]
  },
  "FactionID": {
    "type": "word",
    "value": 5
  },
  "FeatList": {
    "type": "list",
    "value": [
      {
        "__struct_id": 1,
        "Feat": {
          "type": "word",
          "value": 228
        }
      },
      {
        "__struct_id": 1,
        "Feat": {
          "type": "word",
          "value": 289
        }
      }
    ]
  },
  "FirstName": {
    "id": 12827,
    "type": "cexolocstring",
    "value": {
      "0": "Zombie"
    }
  },
  "fortbonus": {
    "type": "short",
    "value": 0
  },
  "Gender": {
    "type": "byte",
    "value": 0
  },
  "GoodEvil": {
    "type": "byte",
    "value": 0
  },
  "HitPoints": {
    "type": "short",
    "value": 16
  },
  "Int": {
    "type": "byte",
    "value": 3
  },
  "Interruptable": {
    "type": "byte",
    "value": 1
  },
  "IsImmortal": {
    "type": "byte",
    "value": 0
  },
  "IsPC": {
    "type": "byte",
    "value": 0
  },
  "LastName": {
    "type": "cexolocstring",
    "value": {}
  },
  "LawfulChaotic": {
    "type": "byte",
    "value": 50
  },
  "Lootable": {
    "type": "byte",
    "value": 0
  },
  "MaxHitPoints": {
    "type": "short",
    "value": 18
  },
  "NaturalAC": {
    "type": "byte",
    "value": 0
  },
  "NoPermDeath": {
    "type": "byte",
    "value": 0
  },
  "PaletteID": {
    "type": "byte",
    "value": 33
  },
  "PerceptionRange": {
    "type": "byte",
    "value": 9
  },
  "Phenotype": {
    "type": "int",
    "value": 0
  },
  "Plot": {
    "type": "byte",
    "value": 0
  },
  "PortraitId": {
    "type": "word",
    "value": 353
  },
  "Race": {
    "type": "byte",
    "value": 24
  },
  "refbonus": {
    "type": "short",
    "value": 0
  },
  "ScriptAttacked": {
    "type": "resref",
    "value": "ai_onattacked"
  },
  "ScriptDamaged": {
    "type": "resref",
    "value": "ai_ondamaged"
  },
  "ScriptDeath": {
    "type": "resref",
    "value": "ai_ondeath"
  },
  "ScriptDialogue": {
    "type": "resref",
    "value": "ai_onconverse"
  },
  "ScriptDisturbed": {
    "type": "resref",
    "value": "ai_ondisturb"
  },
  "ScriptEndRound": {
    "type": "resref",
    "value": "ai_oncombrnd"
  },
  "ScriptHeartbeat": {
    "type": "resref",
    "value": "ai_onheartb"
  },
  "ScriptOnBlocked": {
    "type": "resref",
    "value": "ai_onblocked"
  },
  "ScriptOnNotice": {
    "type": "resref",
    "value": "ai_onpercep"
  },
  "ScriptRested": {
    "type": "resref",
    "value": "ai_onrest"
  },
  "ScriptSpawn": {
    "type": "resref",
    "value": "ai_onspawn"
  },
  "ScriptSpellAt": {
    "type": "resref",
    "value": "ai_onspellcast"
  },
  "ScriptUserDefine": {
    "type": "resref",
    "value": "ai_onuserdef"
  },
  "SkillList": {
    "type": "list",
    "value": [
      {
        "__struct_id": 0,
        "Rank": {
          "type": "byte",
          "value": 0
        }
      },
      {
        "__struct_id": 0,
        "Rank": {
          "type": "byte",
          "value": 0
        }
      },
      {
        "__struct_id": 0,
        "Rank": {
          "type": "byte",
          "value": 0
        }
      },
      {
        "__struct_id": 0,
        "Rank": {
          "type": "byte",
          "value": 0
        }
      },
      {
        "__struct_id": 0,
        "Rank": {
          "type": "byte",
          "value": 0
        }
      },
      {
        "__struct_id": 0,
        "Rank": {
          "type": "byte",
          "value": 0
        }
      },
      {
        "__struct_id": 0,
        "Rank": {
          "type": "byte",
          "value": 0
        }
      },
      {
        "__struct_id": 0,
        "Rank": {
          "type": "byte",
          "value": 0
        }
      },
      {
        "__struct_id": 0,
        "Rank": {
          "type": "byte",
          "value": 0
        }
      },
      {
        "__struct_id": 0,
        "Rank": {
          "type": "byte",
          "value": 0
        }
      },
      {
        "__struct_id": 0,
        "Rank": {
          "type": "byte",
          "value": 0
        }
      },
      {
        "__struct_id": 0,
        "Rank": {
          "type": "byte",
          "value": 0
        }
      },
      {
        "__struct_id": 0,
        "Rank": {
          "type": "byte",
          "value": 0
        }
      },
      {
        "__struct_id": 0,
        "Rank": {
          "type": "byte",
          "value": 0
        }
      },
      {
        "__struct_id": 0,
        "Rank": {
          "type": "byte",
          "value": 0
        }
      },
      {
        "__struct_id": 0,
        "Rank": {
          "type": "byte",
          "value": 0
        }
      },
      {
        "__struct_id": 0,
        "Rank": {
          "type": "byte",
          "value": 0
        }
      },
      {
        "__struct_id": 0,
        "Rank": {
          "type": "byte",
          "value": 0
        }
      },
      {
        "__struct_id": 0,
        "Rank": {
          "type": "byte",
          "value": 0
        }
      },
      {
        "__struct_id": 0,
        "Rank": {
          "type": "byte",
          "value": 0
        }
      },
      {
        "__struct_id": 0,
        "Rank": {
          "type": "byte",
          "value": 0
        }
      },
      {
        "__struct_id": 0,
        "Rank": {
          "type": "byte",
          "value": 0
        }
      },
      {
        "__struct_id": 0,
        "Rank": {
          "type": "byte",
          "value": 0
        }
      },
      {
        "__struct_id": 0,
        "Rank": {
          "type": "byte",
          "value": 0
        }
      },
      {
        "__struct_id": 0,
        "Rank": {
          "type": "byte",
          "value": 0
        }
      },
      {
        "__struct_id": 0,
        "Rank": {
          "type": "byte",
          "value": 0
        }
      },
      {
        "__struct_id": 0,
        "Rank": {
          "type": "byte",
          "value": 0
        }
      },
      {
        "__struct_id": 0,
        "Rank": {
          "type": "byte",
          "value": 0
        }
      }
    ]
  },
  "SoundSetFile": {
    "type": "word",
    "value": 109
  },
  "SpecAbilityList": {
    "type": "list",
    "value": []
  },
  "StartingPackage": {
    "type": "byte",
    "value": 0
  },
  "Str": {
    "type": "byte",
    "value": 12
  },
  "Subrace": {
    "type": "cexostring",
    "value": ""
  },
  "Tag": {
    "type": "cexostring",
    "value": "NW_ZOMBIE01"
  },
  "Tail_New": {
    "type": "dword",
    "value": 205
  },
  "TemplateList": {
    "type": "list",
    "value": []
  },
  "TemplateResRef": {
    "type": "resref",
    "value": "zombie"
  },
  "WalkRate": {
    "type": "int",
    "value": 7
  },
  "willbonus": {
    "type": "short",
    "value": 0
  },
  "Wings_New": {
    "type": "dword",
    "value": 205
  },
  "Wis": {
    "type": "byte",
    "value": 10
  }
}
