{
  "__data_type": "GIT ",
  "AreaProperties": {
    "__struct_id": 100,
    "type": "struct",
    "value": {
      "__struct_id": 100,
      "AmbientSndDay": {
        "type": "int",
        "value": 0
      },
      "AmbientSndDayVol": {
        "type": "int",
        "value": 127
      },
      "AmbientSndNight": {
        "type": "int",
        "value": 0
      },
      "AmbientSndNitVol": {
        "type": "int",
        "value": 127
      },
      "EnvAudio": {
        "type": "int",
        "value": 0
      },
      "MusicBattle": {
        "type": "int",
        "value": 0
      },
      "MusicDay": {
        "type": "int",
        "value": 0
      },
      "MusicDelay": {
        "type": "int",
        "value": 0
      },
      "MusicNight": {
        "type": "int",
        "value": 0
      }
    }
  },
  "Creature List": {
    "type": "list",
    "value": []
  },
  "Door List": {
    "type": "list",
    "value": [
      {
        "__struct_id": 8,
        "AnimationState": {
          "type": "byte",
          "value": 1
        },
        "Appearance": {
          "type": "dword",
          "value": 5017
        },
        "AutoRemoveKey": {
          "type": "byte",
          "value": 0
        },
        "Bearing": {
          "type": "float",
          "value": -0.0
        },
        "CloseLockDC": {
          "type": "byte",
          "value": 0
        },
        "Conversation": {
          "type": "resref",
          "value": ""
        },
        "CurrentHP": {
          "type": "short",
          "value": 80
        },
        "Description": {
          "type": "cexolocstring",
          "value": {}
        },
        "DisarmDC": {
          "type": "byte",
          "value": 15
        },
        "Faction": {
          "type": "dword",
          "value": 1
        },
        "Fort": {
          "type": "byte",
          "value": 16
        },
        "GenericType_New": {
          "type": "dword",
          "value": 0
        },
        "Hardness": {
          "type": "byte",
          "value": 5
        },
        "HP": {
          "type": "short",
          "value": 80
        },
        "Interruptable": {
          "type": "byte",
          "value": 1
        },
        "KeyName": {
          "type": "cexostring",
          "value": ""
        },
        "KeyRequired": {
          "type": "byte",
          "value": 0
        },
        "LinkedTo": {
          "type": "cexostring",
          "value": ""
        },
        "LinkedToFlags": {
          "type": "byte",
          "value": 0
        },
        "LoadScreenID": {
          "type": "word",
          "value": 0
        },
        "Lockable": {
          "type": "byte",
          "value": 0
        },
        "Locked": {
          "type": "byte",
          "value": 0
        },
        "LocName": {
          "id": 5349,
          "type": "cexolocstring",
          "value": {}
        },
        "OnClick": {
          "type": "resref",
          "value": ""
        },
        "OnClosed": {
          "type": "resref",
          "value": ""
        },
        "OnDamaged": {
          "type": "resref",
          "value": ""
        },
        "OnDeath": {
          "type": "resref",
          "value": "x2_door_death"
        },
        "OnDisarm": {
          "type": "resref",
          "value": ""
        },
        "OnFailToOpen": {
          "type": "resref",
          "value": ""
        },
        "OnHeartbeat": {
          "type": "resref",
          "value": ""
        },
        "OnLock": {
          "type": "resref",
          "value": ""
        },
        "OnMeleeAttacked": {
          "type": "resref",
          "value": ""
        },
        "OnOpen": {
          "type": "resref",
          "value": ""
        },
        "OnSpellCastAt": {
          "type": "resref",
          "value": ""
        },
        "OnTrapTriggered": {
          "type": "resref",
          "value": ""
        },
        "OnUnlock": {
          "type": "resref",
          "value": ""
        },
        "OnUserDefined": {
          "type": "resref",
          "value": ""
        },
        "OpenLockDC": {
          "type": "byte",
          "value": 18
        },
        "Plot": {
          "type": "byte",
          "value": 0
        },
        "PortraitId": {
          "type": "word",
          "value": 0
        },
        "Ref": {
          "type": "byte",
          "value": 0
        },
        "Tag": {
          "type": "cexostring",
          "value": "RuralExit"
        },
        "TemplateResRef": {
          "type": "resref",
          "value": "nw_door_ttr_29"
        },
        "TrapDetectable": {
          "type": "byte",
          "value": 1
        },
        "TrapDetectDC": {
          "type": "byte",
          "value": 0
        },
        "TrapDisarmable": {
          "type": "byte",
          "value": 1
        },
        "TrapFlag": {
          "type": "byte",
          "value": 0
        },
        "TrapOneShot": {
          "type": "byte",
          "value": 1
        },
        "TrapType": {
          "type": "byte",
          "value": 0
        },
        "Will": {
          "type": "byte",
          "value": 0
        },
        "X": {
          "type": "float",
          "value": 195.0
        },
        "Y": {
          "type": "float",
          "value": 237.78
        },
        "Z": {
          "type": "float",
          "value": 5.0
        }
      },
      {
        "__struct_id": 8,
        "AnimationState": {
          "type": "byte",
          "value": 1
        },
        "Appearance": {
          "type": "dword",
          "value": 5017
        },
        "AutoRemoveKey": {
          "type": "byte",
          "value": 0
        },
        "Bearing": {
          "type": "float",
          "value": -1.5708
        },
        "CloseLockDC": {
          "type": "byte",
          "value": 0
        },
        "Conversation": {
          "type": "resref",
          "value": ""
        },
        "CurrentHP": {
          "type": "short",
          "value": 80
        },
        "Description": {
          "type": "cexolocstring",
          "value": {}
        },
        "DisarmDC": {
          "type": "byte",
          "value": 15
        },
        "Faction": {
          "type": "dword",
          "value": 1
        },
        "Fort": {
          "type": "byte",
          "value": 16
        },
        "GenericType_New": {
          "type": "dword",
          "value": 0
        },
        "Hardness": {
          "type": "byte",
          "value": 5
        },
        "HP": {
          "type": "short",
          "value": 80
        },
        "Interruptable": {
          "type": "byte",
          "value": 1
        },
        "KeyName": {
          "type": "cexostring",
          "value": ""
        },
        "KeyRequired": {
          "type": "byte",
          "value": 0
        },
        "LinkedTo": {
          "type": "cexostring",
          "value": ""
        },
        "LinkedToFlags": {
          "type": "byte",
          "value": 0
        },
        "LoadScreenID": {
          "type": "word",
          "value": 0
        },
        "Lockable": {
          "type": "byte",
          "value": 0
        },
        "Locked": {
          "type": "byte",
          "value": 0
        },
        "LocName": {
          "id": 5349,
          "type": "cexolocstring",
          "value": {}
        },
        "OnClick": {
          "type": "resref",
          "value": ""
        },
        "OnClosed": {
          "type": "resref",
          "value": ""
        },
        "OnDamaged": {
          "type": "resref",
          "value": ""
        },
        "OnDeath": {
          "type": "resref",
          "value": "x2_door_death"
        },
        "OnDisarm": {
          "type": "resref",
          "value": ""
        },
        "OnFailToOpen": {
          "type": "resref",
          "value": ""
        },
        "OnHeartbeat": {
          "type": "resref",
          "value": ""
        },
        "OnLock": {
          "type": "resref",
          "value": ""
        },
        "OnMeleeAttacked": {
          "type": "resref",
          "value": ""
        },
        "OnOpen": {
          "type": "resref",
          "value": ""
        },
        "OnSpellCastAt": {
          "type": "resref",
          "value": ""
        },
        "OnTrapTriggered": {
          "type": "resref",
          "value": ""
        },
        "OnUnlock": {
          "type": "resref",
          "value": ""
        },
        "OnUserDefined": {
          "type": "resref",
          "value": ""
        },
        "OpenLockDC": {
          "type": "byte",
          "value": 18
        },
        "Plot": {
          "type": "byte",
          "value": 0
        },
        "PortraitId": {
          "type": "word",
          "value": 0
        },
        "Ref": {
          "type": "byte",
          "value": 0
        },
        "Tag": {
          "type": "cexostring",
          "value": "RuralExit"
        },
        "TemplateResRef": {
          "type": "resref",
          "value": "nw_door_ttr_29"
        },
        "TrapDetectable": {
          "type": "byte",
          "value": 1
        },
        "TrapDetectDC": {
          "type": "byte",
          "value": 0
        },
        "TrapDisarmable": {
          "type": "byte",
          "value": 1
        },
        "TrapFlag": {
          "type": "byte",
          "value": 0
        },
        "TrapOneShot": {
          "type": "byte",
          "value": 1
        },
        "TrapType": {
          "type": "byte",
          "value": 0
        },
        "Will": {
          "type": "byte",
          "value": 0
        },
        "X": {
          "type": "float",
          "value": 237.78
        },
        "Y": {
          "type": "float",
          "value": 55.0
        },
        "Z": {
          "type": "float",
          "value": 5.0
        }
      },
      {
        "__struct_id": 8,
        "AnimationState": {
          "type": "byte",
          "value": 0
        },
        "Appearance": {
          "type": "dword",
          "value": 5025
        },
        "AutoRemoveKey": {
          "type": "byte",
          "value": 0
        },
        "Bearing": {
          "type": "float",
          "value": 1.1345
        },
        "CloseLockDC": {
          "type": "byte",
          "value": 0
        },
        "Conversation": {
          "type": "resref",
          "value": ""
        },
        "CurrentHP": {
          "type": "short",
          "value": 80
        },
        "Description": {
          "type": "cexolocstring",
          "value": {}
        },
        "DisarmDC": {
          "type": "byte",
          "value": 15
        },
        "Faction": {
          "type": "dword",
          "value": 1
        },
        "Fort": {
          "type": "byte",
          "value": 16
        },
        "GenericType_New": {
          "type": "dword",
          "value": 0
        },
        "Hardness": {
          "type": "byte",
          "value": 5
        },
        "HP": {
          "type": "short",
          "value": 80
        },
        "Interruptable": {
          "type": "byte",
          "value": 1
        },
        "KeyName": {
          "type": "cexostring",
          "value": ""
        },
        "KeyRequired": {
          "type": "byte",
          "value": 0
        },
        "LinkedTo": {
          "type": "cexostring",
          "value": ""
        },
        "LinkedToFlags": {
          "type": "byte",
          "value": 0
        },
        "LoadScreenID": {
          "type": "word",
          "value": 0
        },
        "Lockable": {
          "type": "byte",
          "value": 0
        },
        "Locked": {
          "type": "byte",
          "value": 0
        },
        "LocName": {
          "id": 5349,
          "type": "cexolocstring",
          "value": {}
        },
        "OnClick": {
          "type": "resref",
          "value": ""
        },
        "OnClosed": {
          "type": "resref",
          "value": ""
        },
        "OnDamaged": {
          "type": "resref",
          "value": ""
        },
        "OnDeath": {
          "type": "resref",
          "value": "x2_door_death"
        },
        "OnDisarm": {
          "type": "resref",
          "value": ""
        },
        "OnFailToOpen": {
          "type": "resref",
          "value": ""
        },
        "OnHeartbeat": {
          "type": "resref",
          "value": ""
        },
        "OnLock": {
          "type": "resref",
          "value": ""
        },
        "OnMeleeAttacked": {
          "type": "resref",
          "value": ""
        },
        "OnOpen": {
          "type": "resref",
          "value": ""
        },
        "OnSpellCastAt": {
          "type": "resref",
          "value": ""
        },
        "OnTrapTriggered": {
          "type": "resref",
          "value": ""
        },
        "OnUnlock": {
          "type": "resref",
          "value": ""
        },
        "OnUserDefined": {
          "type": "resref",
          "value": ""
        },
        "OpenLockDC": {
          "type": "byte",
          "value": 18
        },
        "Plot": {
          "type": "byte",
          "value": 0
        },
        "PortraitId": {
          "type": "word",
          "value": 0
        },
        "Ref": {
          "type": "byte",
          "value": 0
        },
        "Tag": {
          "type": "cexostring",
          "value": "HouseDoor"
        },
        "TemplateResRef": {
          "type": "resref",
          "value": "nw_door_ttr_19"
        },
        "TrapDetectable": {
          "type": "byte",
          "value": 1
        },
        "TrapDetectDC": {
          "type": "byte",
          "value": 0
        },
        "TrapDisarmable": {
          "type": "byte",
          "value": 1
        },
        "TrapFlag": {
          "type": "byte",
          "value": 0
        },
        "TrapOneShot": {
          "type": "byte",
          "value": 1
        },
        "TrapType": {
          "type": "byte",
          "value": 0
        },
        "Will": {
          "type": "byte",
          "value": 0
        },
        "X": {
          "type": "float",
          "value": 77.56999999999999
        },
        "Y": {
          "type": "float",
          "value": 113.84
        },
        "Z": {
          "type": "float",
          "value": 10.55
        }
      },
      {
        "__struct_id": 8,
        "AnimationState": {
          "type": "byte",
          "value": 0
        },
        "Appearance": {
          "type": "dword",
          "value": 5025
        },
        "AutoRemoveKey": {
          "type": "byte",
          "value": 0
        },
        "Bearing": {
          "type": "float",
          "value": -3.1416
        },
        "CloseLockDC": {
          "type": "byte",
          "value": 0
        },
        "Conversation": {
          "type": "resref",
          "value": ""
        },
        "CurrentHP": {
          "type": "short",
          "value": 80
        },
        "Description": {
          "type": "cexolocstring",
          "value": {}
        },
        "DisarmDC": {
          "type": "byte",
          "value": 15
        },
        "Faction": {
          "type": "dword",
          "value": 1
        },
        "Fort": {
          "type": "byte",
          "value": 16
        },
        "GenericType_New": {
          "type": "dword",
          "value": 0
        },
        "Hardness": {
          "type": "byte",
          "value": 5
        },
        "HP": {
          "type": "short",
          "value": 80
        },
        "Interruptable": {
          "type": "byte",
          "value": 1
        },
        "KeyName": {
          "type": "cexostring",
          "value": ""
        },
        "KeyRequired": {
          "type": "byte",
          "value": 0
        },
        "LinkedTo": {
          "type": "cexostring",
          "value": ""
        },
        "LinkedToFlags": {
          "type": "byte",
          "value": 0
        },
        "LoadScreenID": {
          "type": "word",
          "value": 0
        },
        "Lockable": {
          "type": "byte",
          "value": 0
        },
        "Locked": {
          "type": "byte",
          "value": 0
        },
        "LocName": {
          "id": 5349,
          "type": "cexolocstring",
          "value": {}
        },
        "OnClick": {
          "type": "resref",
          "value": ""
        },
        "OnClosed": {
          "type": "resref",
          "value": ""
        },
        "OnDamaged": {
          "type": "resref",
          "value": ""
        },
        "OnDeath": {
          "type": "resref",
          "value": "x2_door_death"
        },
        "OnDisarm": {
          "type": "resref",
          "value": ""
        },
        "OnFailToOpen": {
          "type": "resref",
          "value": ""
        },
        "OnHeartbeat": {
          "type": "resref",
          "value": ""
        },
        "OnLock": {
          "type": "resref",
          "value": ""
        },
        "OnMeleeAttacked": {
          "type": "resref",
          "value": ""
        },
        "OnOpen": {
          "type": "resref",
          "value": ""
        },
        "OnSpellCastAt": {
          "type": "resref",
          "value": ""
        },
        "OnTrapTriggered": {
          "type": "resref",
          "value": ""
        },
        "OnUnlock": {
          "type": "resref",
          "value": ""
        },
        "OnUserDefined": {
          "type": "resref",
          "value": ""
        },
        "OpenLockDC": {
          "type": "byte",
          "value": 18
        },
        "Plot": {
          "type": "byte",
          "value": 0
        },
        "PortraitId": {
          "type": "word",
          "value": 0
        },
        "Ref": {
          "type": "byte",
          "value": 0
        },
        "Tag": {
          "type": "cexostring",
          "value": "HouseDoor"
        },
        "TemplateResRef": {
          "type": "resref",
          "value": "nw_door_ttr_19"
        },
        "TrapDetectable": {
          "type": "byte",
          "value": 1
        },
        "TrapDetectDC": {
          "type": "byte",
          "value": 0
        },
        "TrapDisarmable": {
          "type": "byte",
          "value": 1
        },
        "TrapFlag": {
          "type": "byte",
          "value": 0
        },
        "TrapOneShot": {
          "type": "byte",
          "value": 1
        },
        "TrapType": {
          "type": "byte",
          "value": 0
        },
        "Will": {
          "type": "byte",
          "value": 0
        },
        "X": {
          "type": "float",
          "value": 75.0
        },
        "Y": {
          "type": "float",
          "value": 118.55
        },
        "Z": {
          "type": "float",
          "value": 5.05
        }
      },
      {
        "__struct_id": 8,
        "AnimationState": {
          "type": "byte",
          "value": 1
        },
        "Appearance": {
          "type": "dword",
          "value": 5017
        },
        "AutoRemoveKey": {
          "type": "byte",
          "value": 0
        },
        "Bearing": {
          "type": "float",
          "value": 1.5708
        },
        "CloseLockDC": {
          "type": "byte",
          "value": 0
        },
        "Conversation": {
          "type": "resref",
          "value": ""
        },
        "CurrentHP": {
          "type": "short",
          "value": 80
        },
        "Description": {
          "type": "cexolocstring",
          "value": {}
        },
        "DisarmDC": {
          "type": "byte",
          "value": 15
        },
        "Faction": {
          "type": "dword",
          "value": 1
        },
        "Fort": {
          "type": "byte",
          "value": 16
        },
        "GenericType_New": {
          "type": "dword",
          "value": 0
        },
        "Hardness": {
          "type": "byte",
          "value": 5
        },
        "HP": {
          "type": "short",
          "value": 80
        },
        "Interruptable": {
          "type": "byte",
          "value": 1
        },
        "KeyName": {
          "type": "cexostring",
          "value": ""
        },
        "KeyRequired": {
          "type": "byte",
          "value": 0
        },
        "LinkedTo": {
          "type": "cexostring",
          "value": ""
        },
        "LinkedToFlags": {
          "type": "byte",
          "value": 0
        },
        "LoadScreenID": {
          "type": "word",
          "value": 0
        },
        "Lockable": {
          "type": "byte",
          "value": 0
        },
        "Locked": {
          "type": "byte",
          "value": 0
        },
        "LocName": {
          "id": 5349,
          "type": "cexolocstring",
          "value": {}
        },
        "OnClick": {
          "type": "resref",
          "value": ""
        },
        "OnClosed": {
          "type": "resref",
          "value": ""
        },
        "OnDamaged": {
          "type": "resref",
          "value": ""
        },
        "OnDeath": {
          "type": "resref",
          "value": "x2_door_death"
        },
        "OnDisarm": {
          "type": "resref",
          "value": ""
        },
        "OnFailToOpen": {
          "type": "resref",
          "value": ""
        },
        "OnHeartbeat": {
          "type": "resref",
          "value": ""
        },
        "OnLock": {
          "type": "resref",
          "value": ""
        },
        "OnMeleeAttacked": {
          "type": "resref",
          "value": ""
        },
        "OnOpen": {
          "type": "resref",
          "value": ""
        },
        "OnSpellCastAt": {
          "type": "resref",
          "value": ""
        },
        "OnTrapTriggered": {
          "type": "resref",
          "value": ""
        },
        "OnUnlock": {
          "type": "resref",
          "value": ""
        },
        "OnUserDefined": {
          "type": "resref",
          "value": ""
        },
        "OpenLockDC": {
          "type": "byte",
          "value": 18
        },
        "Plot": {
          "type": "byte",
          "value": 0
        },
        "PortraitId": {
          "type": "word",
          "value": 0
        },
        "Ref": {
          "type": "byte",
          "value": 0
        },
        "Tag": {
          "type": "cexostring",
          "value": "RuralExit"
        },
        "TemplateResRef": {
          "type": "resref",
          "value": "nw_door_ttr_29"
        },
        "TrapDetectable": {
          "type": "byte",
          "value": 1
        },
        "TrapDetectDC": {
          "type": "byte",
          "value": 0
        },
        "TrapDisarmable": {
          "type": "byte",
          "value": 1
        },
        "TrapFlag": {
          "type": "byte",
          "value": 0
        },
        "TrapOneShot": {
          "type": "byte",
          "value": 1
        },
        "TrapType": {
          "type": "byte",
          "value": 0
        },
        "Will": {
          "type": "byte",
          "value": 0
        },
        "X": {
          "type": "float",
          "value": 2.22
        },
        "Y": {
          "type": "float",
          "value": 45.0
        },
        "Z": {
          "type": "float",
          "value": 5.0
        }
      },
      {
        "__struct_id": 8,
        "AnimationState": {
          "type": "byte",
          "value": 0
        },
        "Appearance": {
          "type": "dword",
          "value": 5025
        },
        "AutoRemoveKey": {
          "type": "byte",
          "value": 0
        },
        "Bearing": {
          "type": "float",
          "value": 0.0
        },
        "CloseLockDC": {
          "type": "byte",
          "value": 0
        },
        "Conversation": {
          "type": "resref",
          "value": ""
        },
        "CurrentHP": {
          "type": "short",
          "value": 80
        },
        "Description": {
          "type": "cexolocstring",
          "value": {}
        },
        "DisarmDC": {
          "type": "byte",
          "value": 15
        },
        "Faction": {
          "type": "dword",
          "value": 1
        },
        "Fort": {
          "type": "byte",
          "value": 16
        },
        "GenericType_New": {
          "type": "dword",
          "value": 0
        },
        "Hardness": {
          "type": "byte",
          "value": 5
        },
        "HP": {
          "type": "short",
          "value": 80
        },
        "Interruptable": {
          "type": "byte",
          "value": 1
        },
        "KeyName": {
          "type": "cexostring",
          "value": ""
        },
        "KeyRequired": {
          "type": "byte",
          "value": 0
        },
        "LinkedTo": {
          "type": "cexostring",
          "value": ""
        },
        "LinkedToFlags": {
          "type": "byte",
          "value": 0
        },
        "LoadScreenID": {
          "type": "word",
          "value": 0
        },
        "Lockable": {
          "type": "byte",
          "value": 0
        },
        "Locked": {
          "type": "byte",
          "value": 0
        },
        "LocName": {
          "id": 5349,
          "type": "cexolocstring",
          "value": {}
        },
        "OnClick": {
          "type": "resref",
          "value": ""
        },
        "OnClosed": {
          "type": "resref",
          "value": ""
        },
        "OnDamaged": {
          "type": "resref",
          "value": ""
        },
        "OnDeath": {
          "type": "resref",
          "value": "x2_door_death"
        },
        "OnDisarm": {
          "type": "resref",
          "value": ""
        },
        "OnFailToOpen": {
          "type": "resref",
          "value": ""
        },
        "OnHeartbeat": {
          "type": "resref",
          "value": ""
        },
        "OnLock": {
          "type": "resref",
          "value": ""
        },
        "OnMeleeAttacked": {
          "type": "resref",
          "value": ""
        },
        "OnOpen": {
          "type": "resref",
          "value": ""
        },
        "OnSpellCastAt": {
          "type": "resref",
          "value": ""
        },
        "OnTrapTriggered": {
          "type": "resref",
          "value": ""
        },
        "OnUnlock": {
          "type": "resref",
          "value": ""
        },
        "OnUserDefined": {
          "type": "resref",
          "value": ""
        },
        "OpenLockDC": {
          "type": "byte",
          "value": 18
        },
        "Plot": {
          "type": "byte",
          "value": 0
        },
        "PortraitId": {
          "type": "word",
          "value": 0
        },
        "Ref": {
          "type": "byte",
          "value": 0
        },
        "Tag": {
          "type": "cexostring",
          "value": "HouseDoor"
        },
        "TemplateResRef": {
          "type": "resref",
          "value": "nw_door_ttr_19"
        },
        "TrapDetectable": {
          "type": "byte",
          "value": 1
        },
        "TrapDetectDC": {
          "type": "byte",
          "value": 0
        },
        "TrapDisarmable": {
          "type": "byte",
          "value": 1
        },
        "TrapFlag": {
          "type": "byte",
          "value": 0
        },
        "TrapOneShot": {
          "type": "byte",
          "value": 1
        },
        "TrapType": {
          "type": "byte",
          "value": 0
        },
        "Will": {
          "type": "byte",
          "value": 0
        },
        "X": {
          "type": "float",
          "value": 15.82
        },
        "Y": {
          "type": "float",
          "value": 102.1
        },
        "Z": {
          "type": "float",
          "value": 5.0
        }
      },
      {
        "__struct_id": 8,
        "AnimationState": {
          "type": "byte",
          "value": 0
        },
        "Appearance": {
          "type": "dword",
          "value": 5024
        },
        "AutoRemoveKey": {
          "type": "byte",
          "value": 0
        },
        "Bearing": {
          "type": "float",
          "value": 1.5708
        },
        "CloseLockDC": {
          "type": "byte",
          "value": 0
        },
        "Conversation": {
          "type": "resref",
          "value": ""
        },
        "CurrentHP": {
          "type": "short",
          "value": 80
        },
        "Description": {
          "type": "cexolocstring",
          "value": {}
        },
        "DisarmDC": {
          "type": "byte",
          "value": 15
        },
        "Faction": {
          "type": "dword",
          "value": 1
        },
        "Fort": {
          "type": "byte",
          "value": 16
        },
        "GenericType_New": {
          "type": "dword",
          "value": 0
        },
        "Hardness": {
          "type": "byte",
          "value": 5
        },
        "HP": {
          "type": "short",
          "value": 80
        },
        "Interruptable": {
          "type": "byte",
          "value": 1
        },
        "KeyName": {
          "type": "cexostring",
          "value": ""
        },
        "KeyRequired": {
          "type": "byte",
          "value": 0
        },
        "LinkedTo": {
          "type": "cexostring",
          "value": ""
        },
        "LinkedToFlags": {
          "type": "byte",
          "value": 0
        },
        "LoadScreenID": {
          "type": "word",
          "value": 0
        },
        "Lockable": {
          "type": "byte",
          "value": 0
        },
        "Locked": {
          "type": "byte",
          "value": 0
        },
        "LocName": {
          "id": 5349,
          "type": "cexolocstring",
          "value": {}
        },
        "OnClick": {
          "type": "resref",
          "value": ""
        },
        "OnClosed": {
          "type": "resref",
          "value": ""
        },
        "OnDamaged": {
          "type": "resref",
          "value": ""
        },
        "OnDeath": {
          "type": "resref",
          "value": "x2_door_death"
        },
        "OnDisarm": {
          "type": "resref",
          "value": ""
        },
        "OnFailToOpen": {
          "type": "resref",
          "value": ""
        },
        "OnHeartbeat": {
          "type": "resref",
          "value": ""
        },
        "OnLock": {
          "type": "resref",
          "value": ""
        },
        "OnMeleeAttacked": {
          "type": "resref",
          "value": ""
        },
        "OnOpen": {
          "type": "resref",
          "value": ""
        },
        "OnSpellCastAt": {
          "type": "resref",
          "value": ""
        },
        "OnTrapTriggered": {
          "type": "resref",
          "value": ""
        },
        "OnUnlock": {
          "type": "resref",
          "value": ""
        },
        "OnUserDefined": {
          "type": "resref",
          "value": ""
        },
        "OpenLockDC": {
          "type": "byte",
          "value": 18
        },
        "Plot": {
          "type": "byte",
          "value": 0
        },
        "PortraitId": {
          "type": "word",
          "value": 0
        },
        "Ref": {
          "type": "byte",
          "value": 0
        },
        "Tag": {
          "type": "cexostring",
          "value": "HouseDoor"
        },
        "TemplateResRef": {
          "type": "resref",
          "value": "nw_door_ttr_19"
        },
        "TrapDetectable": {
          "type": "byte",
          "value": 1
        },
        "TrapDetectDC": {
          "type": "byte",
          "value": 0
        },
        "TrapDisarmable": {
          "type": "byte",
          "value": 1
        },
        "TrapFlag": {
          "type": "byte",
          "value": 0
        },
        "TrapOneShot": {
          "type": "byte",
          "value": 1
        },
        "TrapType": {
          "type": "byte",
          "value": 0
        },
        "Will": {
          "type": "byte",
          "value": 0
        },
        "X": {
          "type": "float",
          "value": 17.65
        },
        "Y": {
          "type": "float",
          "value": 105.1
        },
        "Z": {
          "type": "float",
          "value": 8.25
        }
      }
    ]
  },
  "Encounter List": {
    "type": "list",
    "value": []
  },
  "List": {
    "type": "list",
    "value": []
  },
  "Placeable List": {
    "type": "list",
    "value": []
  },
  "SoundList": {
    "type": "list",
    "value": []
  },
  "StoreList": {
    "type": "list",
    "value": []
  },
  "TriggerList": {
    "type": "list",
    "value": []
  },
  "WaypointList": {
    "type": "list",
    "value": []
  }
}
