{
  "__data_type": "UTI ",
  "AddCost": {
    "type": "dword",
    "value": 0
  },
  "BaseItem": {
    "type": "int",
    "value": 80
  },
  "Charges": {
    "type": "byte",
    "value": 0
  },
  "Cloth1Color": {
    "type": "byte",
    "value": 167
  },
  "Cloth2Color": {
    "type": "byte",
    "value": 167
  },
  "Comment": {
    "type": "cexostring",
    "value": ""
  },
  "Cost": {
    "type": "dword",
    "value": 24
  },
  "Cursed": {
    "type": "byte",
    "value": 0
  },
  "DescIdentified": {
    "id": 66528,
    "type": "cexolocstring",
    "value": {}
  },
  "Description": {
    "type": "cexolocstring",
    "value": {}
  },
  "Identified": {
    "type": "byte",
    "value": 1
  },
  "Leather1Color": {
    "type": "byte",
    "value": 167
  },
  "Leather2Color": {
    "type": "byte",
    "value": 167
  },
  "LocalizedName": {
    "id": 66540,
    "type": "cexolocstring",
    "value": {
      "0": "Tomi's Cloak"
    }
  },
  "Metal1Color": {
    "type": "byte",
    "value": 2
  },
  "Metal2Color": {
    "type": "byte",
    "value": 2
  },
  "ModelPart1": {
    "type": "byte",
    "value": 5
  },
  "PaletteID": {
    "type": "byte",
    "value": 3
  },
  "Plot": {
    "type": "byte",
    "value": 0
  },
  "PropertiesList": {
    "type": "list",
    "value": []
  },
  "StackSize": {
    "type": "word",
    "value": 1
  },
  "Stolen": {
    "type": "byte",
    "value": 0
  },
  "Tag": {
    "type": "cexostring",
    "value": "X0_MAARCL027"
  },
  "TemplateResRef": {
    "type": "resref",
    "value": "hen_tomic"
  }
}
