{
  "__data_type": "DLG ",
  "DelayEntry": {
    "type": "dword",
    "value": 0
  },
  "DelayReply": {
    "type": "dword",
    "value": 0
  },
  "EndConverAbort": {
    "type": "resref",
    "value": ""
  },
  "EndConversation": {
    "type": "resref",
    "value": ""
  },
  "EntryList": {
    "type": "list",
    "value": [
      {
        "__struct_id": 0,
        "Animation": {
          "type": "dword",
          "value": 29
        },
        "AnimLoop": {
          "type": "byte",
          "value": 1
        },
        "Comment": {
          "type": "cexostring",
          "value": ""
        },
        "Delay": {
          "type": "dword",
          "value": 4294967295
        },
        "Quest": {
          "type": "cexostring",
          "value": ""
        },
        "RepliesList": {
          "type": "list",
          "value": [
            {
              "__struct_id": 0,
              "Active": {
                "type": "resref",
                "value": "nw_d2_intn"
              },
              "Index": {
                "type": "dword",
                "value": 25
              },
              "IsChild": {
                "type": "byte",
                "value": 0
              }
            },
            {
              "__struct_id": 1,
              "Active": {
                "type": "resref",
                "value": "nw_d2_intn"
              },
              "Index": {
                "type": "dword",
                "value": 4
              },
              "IsChild": {
                "type": "byte",
                "value": 0
              }
            },
            {
              "__struct_id": 2,
              "Active": {
                "type": "resref",
                "value": "nw_d2_intn"
              },
              "Index": {
                "type": "dword",
                "value": 3
              },
              "IsChild": {
                "type": "byte",
                "value": 0
              }
            },
            {
              "__struct_id": 3,
              "Active": {
                "type": "resref",
                "value": "nw_d2_intl"
              },
              "Index": {
                "type": "dword",
                "value": 2
              },
              "IsChild": {
                "type": "byte",
                "value": 0
              }
            },
            {
              "__struct_id": 4,
              "Active": {
                "type": "resref",
                "value": "nw_d2_intl"
              },
              "Index": {
                "type": "dword",
                "value": 1
              },
              "IsChild": {
                "type": "byte",
                "value": 0
              }
            },
            {
              "__struct_id": 5,
              "Active": {
                "type": "resref",
                "value": "nw_d2_intl"
              },
              "Index": {
                "type": "dword",
                "value": 0
              },
              "IsChild": {
                "type": "byte",
                "value": 0
              }
            }
          ]
        },
        "Script": {
          "type": "resref",
          "value": "m2q1aballtalk"
        },
        "Sound": {
          "type": "resref",
          "value": "vs_nelfxxm1_052"
        },
        "Speaker": {
          "type": "cexostring",
          "value": ""
        },
        "Text": {
          "id": 32046,
          "type": "cexolocstring",
          "value": {}
        }
      },
      {
        "__struct_id": 1,
        "Animation": {
          "type": "dword",
          "value": 0
        },
        "AnimLoop": {
          "type": "byte",
          "value": 1
        },
        "Comment": {
          "type": "cexostring",
          "value": ""
        },
        "Delay": {
          "type": "dword",
          "value": 4294967295
        },
        "Quest": {
          "type": "cexostring",
          "value": ""
        },
        "RepliesList": {
          "type": "list",
          "value": []
        },
        "Script": {
          "type": "resref",
          "value": ""
        },
        "Sound": {
          "type": "resref",
          "value": ""
        },
        "Speaker": {
          "type": "cexostring",
          "value": ""
        },
        "Text": {
          "id": 32050,
          "type": "cexolocstring",
          "value": {}
        }
      },
      {
        "__struct_id": 2,
        "Animation": {
          "type": "dword",
          "value": 0
        },
        "AnimLoop": {
          "type": "byte",
          "value": 1
        },
        "Comment": {
          "type": "cexostring",
          "value": ""
        },
        "Delay": {
          "type": "dword",
          "value": 4294967295
        },
        "Quest": {
          "type": "cexostring",
          "value": ""
        },
        "RepliesList": {
          "type": "list",
          "value": [
            {
              "__struct_id": 0,
              "Active": {
                "type": "resref",
                "value": ""
              },
              "Index": {
                "type": "dword",
                "value": 5
              },
              "IsChild": {
                "type": "byte",
                "value": 0
              }
            }
          ]
        },
        "Script": {
          "type": "resref",
          "value": ""
        },
        "Sound": {
          "type": "resref",
          "value": ""
        },
        "Speaker": {
          "type": "cexostring",
          "value": ""
        },
        "Text": {
          "id": 32049,
          "type": "cexolocstring",
          "value": {}
        }
      },
      {
        "__struct_id": 3,
        "Animation": {
          "type": "dword",
          "value": 0
        },
        "AnimLoop": {
          "type": "byte",
          "value": 1
        },
        "Comment": {
          "type": "cexostring",
          "value": ""
        },
        "Delay": {
          "type": "dword",
          "value": 4294967295
        },
        "Quest": {
          "type": "cexostring",
          "value": ""
        },
        "RepliesList": {
          "type": "list",
          "value": [
            {
              "__struct_id": 0,
              "Active": {
                "type": "resref",
                "value": "nw_d2_intn"
              },
              "Index": {
                "type": "dword",
                "value": 11
              },
              "IsChild": {
                "type": "byte",
                "value": 0
              }
            },
            {
              "__struct_id": 1,
              "Active": {
                "type": "resref",
                "value": "nw_d2_intn"
              },
              "Index": {
                "type": "dword",
                "value": 10
              },
              "IsChild": {
                "type": "byte",
                "value": 0
              }
            },
            {
              "__struct_id": 2,
              "Active": {
                "type": "resref",
                "value": "nw_d2_intn"
              },
              "Index": {
                "type": "dword",
                "value": 9
              },
              "IsChild": {
                "type": "byte",
                "value": 0
              }
            },
            {
              "__struct_id": 3,
              "Active": {
                "type": "resref",
                "value": "nw_d2_intl"
              },
              "Index": {
                "type": "dword",
                "value": 8
              },
              "IsChild": {
                "type": "byte",
                "value": 0
              }
            },
            {
              "__struct_id": 4,
              "Active": {
                "type": "resref",
                "value": "nw_d2_intl"
              },
              "Index": {
                "type": "dword",
                "value": 7
              },
              "IsChild": {
                "type": "byte",
                "value": 0
              }
            },
            {
              "__struct_id": 5,
              "Active": {
                "type": "resref",
                "value": "nw_d2_intl"
              },
              "Index": {
                "type": "dword",
                "value": 6
              },
              "IsChild": {
                "type": "byte",
                "value": 0
              }
            }
          ]
        },
        "Script": {
          "type": "resref",
          "value": ""
        },
        "Sound": {
          "type": "resref",
          "value": ""
        },
        "Speaker": {
          "type": "cexostring",
          "value": ""
        },
        "Text": {
          "id": 32052,
          "type": "cexolocstring",
          "value": {}
        }
      },
      {
        "__struct_id": 4,
        "Animation": {
          "type": "dword",
          "value": 0
        },
        "AnimLoop": {
          "type": "byte",
          "value": 1
        },
        "Comment": {
          "type": "cexostring",
          "value": ""
        },
        "Delay": {
          "type": "dword",
          "value": 4294967295
        },
        "Quest": {
          "type": "cexostring",
          "value": ""
        },
        "RepliesList": {
          "type": "list",
          "value": [
            {
              "__struct_id": 0,
              "Active": {
                "type": "resref",
                "value": ""
              },
              "Index": {
                "type": "dword",
                "value": 12
              },
              "IsChild": {
                "type": "byte",
                "value": 0
              }
            }
          ]
        },
        "Script": {
          "type": "resref",
          "value": ""
        },
        "Sound": {
          "type": "resref",
          "value": ""
        },
        "Speaker": {
          "type": "cexostring",
          "value": ""
        },
        "Text": {
          "id": 32051,
          "type": "cexolocstring",
          "value": {}
        }
      },
      {
        "__struct_id": 5,
        "Animation": {
          "type": "dword",
          "value": 0
        },
        "AnimLoop": {
          "type": "byte",
          "value": 1
        },
        "Comment": {
          "type": "cexostring",
          "value": ""
        },
        "Delay": {
          "type": "dword",
          "value": 4294967295
        },
        "Quest": {
          "type": "cexostring",
          "value": "m2q2_Main"
        },
        "QuestEntry": {
          "type": "dword",
          "value": 10
        },
        "RepliesList": {
          "type": "list",
          "value": [
            {
              "__struct_id": 0,
              "Active": {
                "type": "resref",
                "value": "nw_d2_intn"
              },
              "Index": {
                "type": "dword",
                "value": 20
              },
              "IsChild": {
                "type": "byte",
                "value": 0
              }
            },
            {
              "__struct_id": 1,
              "Active": {
                "type": "resref",
                "value": "nw_d2_intn"
              },
              "Index": {
                "type": "dword",
                "value": 19
              },
              "IsChild": {
                "type": "byte",
                "value": 0
              }
            },
            {
              "__struct_id": 2,
              "Active": {
                "type": "resref",
                "value": "nw_d2_intn"
              },
              "Index": {
                "type": "dword",
                "value": 18
              },
              "IsChild": {
                "type": "byte",
                "value": 0
              }
            },
            {
              "__struct_id": 3,
              "Active": {
                "type": "resref",
                "value": "nw_d2_intn"
              },
              "Index": {
                "type": "dword",
                "value": 17
              },
              "IsChild": {
                "type": "byte",
                "value": 0
              }
            },
            {
              "__struct_id": 4,
              "Active": {
                "type": "resref",
                "value": "nw_d2_intl"
              },
              "Index": {
                "type": "dword",
                "value": 16
              },
              "IsChild": {
                "type": "byte",
                "value": 0
              }
            },
            {
              "__struct_id": 5,
              "Active": {
                "type": "resref",
                "value": "nw_d2_intl"
              },
              "Index": {
                "type": "dword",
                "value": 15
              },
              "IsChild": {
                "type": "byte",
                "value": 0
              }
            },
            {
              "__struct_id": 6,
              "Active": {
                "type": "resref",
                "value": "nw_d2_intl"
              },
              "Index": {
                "type": "dword",
                "value": 14
              },
              "IsChild": {
                "type": "byte",
                "value": 0
              }
            },
            {
              "__struct_id": 7,
              "Active": {
                "type": "resref",
                "value": "nw_d2_intl"
              },
              "Index": {
                "type": "dword",
                "value": 13
              },
              "IsChild": {
                "type": "byte",
                "value": 0
              }
            }
          ]
        },
        "Script": {
          "type": "resref",
          "value": ""
        },
        "Sound": {
          "type": "resref",
          "value": ""
        },
        "Speaker": {
          "type": "cexostring",
          "value": ""
        },
        "Text": {
          "id": 32053,
          "type": "cexolocstring",
          "value": {}
        }
      },
      {
        "__struct_id": 6,
        "Animation": {
          "type": "dword",
          "value": 0
        },
        "AnimLoop": {
          "type": "byte",
          "value": 1
        },
        "Comment": {
          "type": "cexostring",
          "value": ""
        },
        "Delay": {
          "type": "dword",
          "value": 4294967295
        },
        "Quest": {
          "type": "cexostring",
          "value": ""
        },
        "RepliesList": {
          "type": "list",
          "value": [
            {
              "__struct_id": 0,
              "Active": {
                "type": "resref",
                "value": "nw_d2_intn"
              },
              "Index": {
                "type": "dword",
                "value": 20
              },
              "IsChild": {
                "type": "byte",
                "value": 1
              },
              "LinkComment": {
                "type": "cexostring",
                "value": ""
              }
            },
            {
              "__struct_id": 1,
              "Active": {
                "type": "resref",
                "value": "nw_d2_intn"
              },
              "Index": {
                "type": "dword",
                "value": 19
              },
              "IsChild": {
                "type": "byte",
                "value": 1
              },
              "LinkComment": {
                "type": "cexostring",
                "value": ""
              }
            },
            {
              "__struct_id": 2,
              "Active": {
                "type": "resref",
                "value": "nw_d2_intn"
              },
              "Index": {
                "type": "dword",
                "value": 17
              },
              "IsChild": {
                "type": "byte",
                "value": 1
              },
              "LinkComment": {
                "type": "cexostring",
                "value": ""
              }
            },
            {
              "__struct_id": 3,
              "Active": {
                "type": "resref",
                "value": "nw_d2_intl"
              },
              "Index": {
                "type": "dword",
                "value": 16
              },
              "IsChild": {
                "type": "byte",
                "value": 1
              },
              "LinkComment": {
                "type": "cexostring",
                "value": ""
              }
            },
            {
              "__struct_id": 4,
              "Active": {
                "type": "resref",
                "value": "nw_d2_intl"
              },
              "Index": {
                "type": "dword",
                "value": 15
              },
              "IsChild": {
                "type": "byte",
                "value": 1
              },
              "LinkComment": {
                "type": "cexostring",
                "value": ""
              }
            },
            {
              "__struct_id": 5,
              "Active": {
                "type": "resref",
                "value": "nw_d2_intl"
              },
              "Index": {
                "type": "dword",
                "value": 13
              },
              "IsChild": {
                "type": "byte",
                "value": 1
              },
              "LinkComment": {
                "type": "cexostring",
                "value": ""
              }
            }
          ]
        },
        "Script": {
          "type": "resref",
          "value": ""
        },
        "Sound": {
          "type": "resref",
          "value": ""
        },
        "Speaker": {
          "type": "cexostring",
          "value": ""
        },
        "Text": {
          "id": 32056,
          "type": "cexolocstring",
          "value": {}
        }
      },
      {
        "__struct_id": 7,
        "Animation": {
          "type": "dword",
          "value": 0
        },
        "AnimLoop": {
          "type": "byte",
          "value": 1
        },
        "Comment": {
          "type": "cexostring",
          "value": ""
        },
        "Delay": {
          "type": "dword",
          "value": 4294967295
        },
        "Quest": {
          "type": "cexostring",
          "value": ""
        },
        "RepliesList": {
          "type": "list",
          "value": [
            {
              "__struct_id": 0,
              "Active": {
                "type": "resref",
                "value": "nw_d2_intn"
              },
              "Index": {
                "type": "dword",
                "value": 20
              },
              "IsChild": {
                "type": "byte",
                "value": 1
              },
              "LinkComment": {
                "type": "cexostring",
                "value": ""
              }
            },
            {
              "__struct_id": 1,
              "Active": {
                "type": "resref",
                "value": "nw_d2_intn"
              },
              "Index": {
                "type": "dword",
                "value": 18
              },
              "IsChild": {
                "type": "byte",
                "value": 1
              },
              "LinkComment": {
                "type": "cexostring",
                "value": ""
              }
            },
            {
              "__struct_id": 2,
              "Active": {
                "type": "resref",
                "value": "nw_d2_intn"
              },
              "Index": {
                "type": "dword",
                "value": 17
              },
              "IsChild": {
                "type": "byte",
                "value": 1
              },
              "LinkComment": {
                "type": "cexostring",
                "value": ""
              }
            },
            {
              "__struct_id": 3,
              "Active": {
                "type": "resref",
                "value": "nw_d2_intl"
              },
              "Index": {
                "type": "dword",
                "value": 16
              },
              "IsChild": {
                "type": "byte",
                "value": 1
              },
              "LinkComment": {
                "type": "cexostring",
                "value": ""
              }
            },
            {
              "__struct_id": 4,
              "Active": {
                "type": "resref",
                "value": "nw_d2_intl"
              },
              "Index": {
                "type": "dword",
                "value": 14
              },
              "IsChild": {
                "type": "byte",
                "value": 1
              },
              "LinkComment": {
                "type": "cexostring",
                "value": ""
              }
            },
            {
              "__struct_id": 5,
              "Active": {
                "type": "resref",
                "value": "nw_d2_intl"
              },
              "Index": {
                "type": "dword",
                "value": 13
              },
              "IsChild": {
                "type": "byte",
                "value": 1
              },
              "LinkComment": {
                "type": "cexostring",
                "value": ""
              }
            }
          ]
        },
        "Script": {
          "type": "resref",
          "value": ""
        },
        "Sound": {
          "type": "resref",
          "value": ""
        },
        "Speaker": {
          "type": "cexostring",
          "value": ""
        },
        "Text": {
          "id": 32055,
          "type": "cexolocstring",
          "value": {}
        }
      },
      {
        "__struct_id": 8,
        "Animation": {
          "type": "dword",
          "value": 0
        },
        "AnimLoop": {
          "type": "byte",
          "value": 1
        },
        "Comment": {
          "type": "cexostring",
          "value": ""
        },
        "Delay": {
          "type": "dword",
          "value": 4294967295
        },
        "Quest": {
          "type": "cexostring",
          "value": ""
        },
        "RepliesList": {
          "type": "list",
          "value": [
            {
              "__struct_id": 0,
              "Active": {
                "type": "resref",
                "value": "nw_d2_intn"
              },
              "Index": {
                "type": "dword",
                "value": 24
              },
              "IsChild": {
                "type": "byte",
                "value": 0
              }
            },
            {
              "__struct_id": 1,
              "Active": {
                "type": "resref",
                "value": "nw_d2_intl"
              },
              "Index": {
                "type": "dword",
                "value": 23
              },
              "IsChild": {
                "type": "byte",
                "value": 0
              }
            },
            {
              "__struct_id": 2,
              "Active": {
                "type": "resref",
                "value": "nw_d2_intn"
              },
              "Index": {
                "type": "dword",
                "value": 22
              },
              "IsChild": {
                "type": "byte",
                "value": 0
              }
            },
            {
              "__struct_id": 3,
              "Active": {
                "type": "resref",
                "value": "nw_d2_intl"
              },
              "Index": {
                "type": "dword",
                "value": 21
              },
              "IsChild": {
                "type": "byte",
                "value": 0
              }
            }
          ]
        },
        "Script": {
          "type": "resref",
          "value": ""
        },
        "Sound": {
          "type": "resref",
          "value": ""
        },
        "Speaker": {
          "type": "cexostring",
          "value": ""
        },
        "Text": {
          "id": 32054,
          "type": "cexolocstring",
          "value": {}
        }
      },
      {
        "__struct_id": 9,
        "Animation": {
          "type": "dword",
          "value": 0
        },
        "AnimLoop": {
          "type": "byte",
          "value": 1
        },
        "Comment": {
          "type": "cexostring",
          "value": ""
        },
        "Delay": {
          "type": "dword",
          "value": 4294967295
        },
        "Quest": {
          "type": "cexostring",
          "value": ""
        },
        "RepliesList": {
          "type": "list",
          "value": []
        },
        "Script": {
          "type": "resref",
          "value": "nw_d1_shopnatur2"
        },
        "Sound": {
          "type": "resref",
          "value": ""
        },
        "Speaker": {
          "type": "cexostring",
          "value": ""
        },
        "Text": {
          "id": 32059,
          "type": "cexolocstring",
          "value": {}
        }
      },
      {
        "__struct_id": 10,
        "Animation": {
          "type": "dword",
          "value": 0
        },
        "AnimLoop": {
          "type": "byte",
          "value": 1
        },
        "Comment": {
          "type": "cexostring",
          "value": ""
        },
        "Delay": {
          "type": "dword",
          "value": 4294967295
        },
        "Quest": {
          "type": "cexostring",
          "value": ""
        },
        "RepliesList": {
          "type": "list",
          "value": []
        },
        "Script": {
          "type": "resref",
          "value": ""
        },
        "Sound": {
          "type": "resref",
          "value": ""
        },
        "Speaker": {
          "type": "cexostring",
          "value": ""
        },
        "Text": {
          "id": 32058,
          "type": "cexolocstring",
          "value": {}
        }
      },
      {
        "__struct_id": 11,
        "Animation": {
          "type": "dword",
          "value": 0
        },
        "AnimLoop": {
          "type": "byte",
          "value": 1
        },
        "Comment": {
          "type": "cexostring",
          "value": ""
        },
        "Delay": {
          "type": "dword",
          "value": 4294967295
        },
        "Quest": {
          "type": "cexostring",
          "value": ""
        },
        "RepliesList": {
          "type": "list",
          "value": [
            {
              "__struct_id": 0,
              "Active": {
                "type": "resref",
                "value": ""
              },
              "Index": {
                "type": "dword",
                "value": 26
              },
              "IsChild": {
                "type": "byte",
                "value": 0
              }
            }
          ]
        },
        "Script": {
          "type": "resref",
          "value": ""
        },
        "Sound": {
          "type": "resref",
          "value": ""
        },
        "Speaker": {
          "type": "cexostring",
          "value": ""
        },
        "Text": {
          "id": 32048,
          "type": "cexolocstring",
          "value": {}
        }
      },
      {
        "__struct_id": 12,
        "Animation": {
          "type": "dword",
          "value": 29
        },
        "AnimLoop": {
          "type": "byte",
          "value": 1
        },
        "Comment": {
          "type": "cexostring",
          "value": ""
        },
        "Delay": {
          "type": "dword",
          "value": 4294967295
        },
        "Quest": {
          "type": "cexostring",
          "value": ""
        },
        "RepliesList": {
          "type": "list",
          "value": [
            {
              "__struct_id": 0,
              "Active": {
                "type": "resref",
                "value": "nw_d2_intn"
              },
              "Index": {
                "type": "dword",
                "value": 32
              },
              "IsChild": {
                "type": "byte",
                "value": 0
              }
            },
            {
              "__struct_id": 1,
              "Active": {
                "type": "resref",
                "value": "nw_d2_intn"
              },
              "Index": {
                "type": "dword",
                "value": 31
              },
              "IsChild": {
                "type": "byte",
                "value": 0
              }
            },
            {
              "__struct_id": 2,
              "Active": {
                "type": "resref",
                "value": "nw_d2_intn"
              },
              "Index": {
                "type": "dword",
                "value": 22
              },
              "IsChild": {
                "type": "byte",
                "value": 1
              },
              "LinkComment": {
                "type": "cexostring",
                "value": ""
              }
            },
            {
              "__struct_id": 3,
              "Active": {
                "type": "resref",
                "value": "nw_d2_intn"
              },
              "Index": {
                "type": "dword",
                "value": 30
              },
              "IsChild": {
                "type": "byte",
                "value": 0
              }
            },
            {
              "__struct_id": 4,
              "Active": {
                "type": "resref",
                "value": "nw_d2_intl"
              },
              "Index": {
                "type": "dword",
                "value": 29
              },
              "IsChild": {
                "type": "byte",
                "value": 0
              }
            },
            {
              "__struct_id": 5,
              "Active": {
                "type": "resref",
                "value": "nw_d2_intl"
              },
              "Index": {
                "type": "dword",
                "value": 28
              },
              "IsChild": {
                "type": "byte",
                "value": 0
              }
            },
            {
              "__struct_id": 6,
              "Active": {
                "type": "resref",
                "value": "nw_d2_intl"
              },
              "Index": {
                "type": "dword",
                "value": 21
              },
              "IsChild": {
                "type": "byte",
                "value": 1
              },
              "LinkComment": {
                "type": "cexostring",
                "value": ""
              }
            },
            {
              "__struct_id": 7,
              "Active": {
                "type": "resref",
                "value": "nw_d2_intl"
              },
              "Index": {
                "type": "dword",
                "value": 27
              },
              "IsChild": {
                "type": "byte",
                "value": 0
              }
            }
          ]
        },
        "Script": {
          "type": "resref",
          "value": ""
        },
        "Sound": {
          "type": "resref",
          "value": "vs_nelfxxm1_051"
        },
        "Speaker": {
          "type": "cexostring",
          "value": ""
        },
        "Text": {
          "id": 32047,
          "type": "cexolocstring",
          "value": {}
        }
      },
      {
        "__struct_id": 13,
        "Animation": {
          "type": "dword",
          "value": 34
        },
        "AnimLoop": {
          "type": "byte",
          "value": 1
        },
        "Comment": {
          "type": "cexostring",
          "value": ""
        },
        "Delay": {
          "type": "dword",
          "value": 4294967295
        },
        "Quest": {
          "type": "cexostring",
          "value": ""
        },
        "RepliesList": {
          "type": "list",
          "value": [
            {
              "__struct_id": 0,
              "Active": {
                "type": "resref",
                "value": "nw_d2_intn"
              },
              "Index": {
                "type": "dword",
                "value": 22
              },
              "IsChild": {
                "type": "byte",
                "value": 1
              },
              "LinkComment": {
                "type": "cexostring",
                "value": ""
              }
            },
            {
              "__struct_id": 1,
              "Active": {
                "type": "resref",
                "value": "nw_d2_intl"
              },
              "Index": {
                "type": "dword",
                "value": 21
              },
              "IsChild": {
                "type": "byte",
                "value": 1
              },
              "LinkComment": {
                "type": "cexostring",
                "value": ""
              }
            },
            {
              "__struct_id": 2,
              "Active": {
                "type": "resref",
                "value": ""
              },
              "Index": {
                "type": "dword",
                "value": 33
              },
              "IsChild": {
                "type": "byte",
                "value": 0
              }
            }
          ]
        },
        "Script": {
          "type": "resref",
          "value": ""
        },
        "Sound": {
          "type": "resref",
          "value": "vs_nelfxxm1_050"
        },
        "Speaker": {
          "type": "cexostring",
          "value": ""
        },
        "Text": {
          "id": 32057,
          "type": "cexolocstring",
          "value": {}
        }
      },
      {
        "__struct_id": 14,
        "Animation": {
          "type": "dword",
          "value": 0
        },
        "AnimLoop": {
          "type": "byte",
          "value": 1
        },
        "Comment": {
          "type": "cexostring",
          "value": ""
        },
        "Delay": {
          "type": "dword",
          "value": 4294967295
        },
        "Quest": {
          "type": "cexostring",
          "value": ""
        },
        "RepliesList": {
          "type": "list",
          "value": []
        },
        "Script": {
          "type": "resref",
          "value": ""
        },
        "Sound": {
          "type": "resref",
          "value": ""
        },
        "Speaker": {
          "type": "cexostring",
          "value": ""
        },
        "Text": {
          "id": 68097,
          "type": "cexolocstring",
          "value": {}
        }
      },
      {
        "__struct_id": 15,
        "Animation": {
          "type": "dword",
          "value": 0
        },
        "AnimLoop": {
          "type": "byte",
          "value": 1
        },
        "Comment": {
          "type": "cexostring",
          "value": ""
        },
        "Delay": {
          "type": "dword",
          "value": 4294967295
        },
        "Quest": {
          "type": "cexostring",
          "value": ""
        },
        "RepliesList": {
          "type": "list",
          "value": [
            {
              "__struct_id": 0,
              "Active": {
                "type": "resref",
                "value": "nw_d2_intn"
              },
              "Index": {
                "type": "dword",
                "value": 22
              },
              "IsChild": {
                "type": "byte",
                "value": 1
              },
              "LinkComment": {
                "type": "cexostring",
                "value": ""
              }
            },
            {
              "__struct_id": 1,
              "Active": {
                "type": "resref",
                "value": "nw_d2_intl"
              },
              "Index": {
                "type": "dword",
                "value": 21
              },
              "IsChild": {
                "type": "byte",
                "value": 1
              },
              "LinkComment": {
                "type": "cexostring",
                "value": ""
              }
            },
            {
              "__struct_id": 2,
              "Active": {
                "type": "resref",
                "value": ""
              },
              "Index": {
                "type": "dword",
                "value": 34
              },
              "IsChild": {
                "type": "byte",
                "value": 0
              }
            }
          ]
        },
        "Script": {
          "type": "resref",
          "value": ""
        },
        "Sound": {
          "type": "resref",
          "value": ""
        },
        "Speaker": {
          "type": "cexostring",
          "value": ""
        },
        "Text": {
          "id": 68098,
          "type": "cexolocstring",
          "value": {}
        }
      },
      {
        "__struct_id": 16,
        "Animation": {
          "type": "dword",
          "value": 0
        },
        "AnimLoop": {
          "type": "byte",
          "value": 1
        },
        "Comment": {
          "type": "cexostring",
          "value": ""
        },
        "Delay": {
          "type": "dword",
          "value": 4294967295
        },
        "Quest": {
          "type": "cexostring",
          "value": ""
        },
        "RepliesList": {
          "type": "list",
          "value": []
        },
        "Script": {
          "type": "resref",
          "value": ""
        },
        "Sound": {
          "type": "resref",
          "value": ""
        },
        "Speaker": {
          "type": "cexostring",
          "value": ""
        },
        "Text": {
          "id": 68099,
          "type": "cexolocstring",
          "value": {}
        }
      }
    ]
  },
  "NumWords": {
    "type": "dword",
    "value": 538
  },
  "ReplyList": {
    "type": "list",
    "value": [
      {
        "__struct_id": 0,
        "Animation": {
          "type": "dword",
          "value": 0
        },
        "AnimLoop": {
          "type": "byte",
          "value": 1
        },
        "Comment": {
          "type": "cexostring",
          "value": ""
        },
        "Delay": {
          "type": "dword",
          "value": 4294967295
        },
        "EntriesList": {
          "type": "list",
          "value": [
            {
              "__struct_id": 0,
              "Active": {
                "type": "resref",
                "value": ""
              },
              "Index": {
                "type": "dword",
                "value": 1
              },
              "IsChild": {
                "type": "byte",
                "value": 1
              },
              "LinkComment": {
                "type": "cexostring",
                "value": ""
              }
            }
          ]
        },
        "Quest": {
          "type": "cexostring",
          "value": ""
        },
        "Script": {
          "type": "resref",
          "value": ""
        },
        "Sound": {
          "type": "resref",
          "value": ""
        },
        "Text": {
          "id": 32021,
          "type": "cexolocstring",
          "value": {}
        }
      },
      {
        "__struct_id": 1,
        "Animation": {
          "type": "dword",
          "value": 0
        },
        "AnimLoop": {
          "type": "byte",
          "value": 1
        },
        "Comment": {
          "type": "cexostring",
          "value": ""
        },
        "Delay": {
          "type": "dword",
          "value": 4294967295
        },
        "EntriesList": {
          "type": "list",
          "value": [
            {
              "__struct_id": 0,
              "Active": {
                "type": "resref",
                "value": ""
              },
              "Index": {
                "type": "dword",
                "value": 2
              },
              "IsChild": {
                "type": "byte",
                "value": 1
              },
              "LinkComment": {
                "type": "cexostring",
                "value": ""
              }
            }
          ]
        },
        "Quest": {
          "type": "cexostring",
          "value": ""
        },
        "Script": {
          "type": "resref",
          "value": ""
        },
        "Sound": {
          "type": "resref",
          "value": ""
        },
        "Text": {
          "id": 32020,
          "type": "cexolocstring",
          "value": {}
        }
      },
      {
        "__struct_id": 2,
        "Animation": {
          "type": "dword",
          "value": 0
        },
        "AnimLoop": {
          "type": "byte",
          "value": 1
        },
        "Comment": {
          "type": "cexostring",
          "value": ""
        },
        "Delay": {
          "type": "dword",
          "value": 4294967295
        },
        "EntriesList": {
          "type": "list",
          "value": [
            {
              "__struct_id": 0,
              "Active": {
                "type": "resref",
                "value": ""
              },
              "Index": {
                "type": "dword",
                "value": 11
              },
              "IsChild": {
                "type": "byte",
                "value": 1
              },
              "LinkComment": {
                "type": "cexostring",
                "value": ""
              }
            }
          ]
        },
        "Quest": {
          "type": "cexostring",
          "value": ""
        },
        "Script": {
          "type": "resref",
          "value": ""
        },
        "Sound": {
          "type": "resref",
          "value": ""
        },
        "Text": {
          "id": 32019,
          "type": "cexolocstring",
          "value": {}
        }
      },
      {
        "__struct_id": 3,
        "Animation": {
          "type": "dword",
          "value": 0
        },
        "AnimLoop": {
          "type": "byte",
          "value": 1
        },
        "Comment": {
          "type": "cexostring",
          "value": ""
        },
        "Delay": {
          "type": "dword",
          "value": 4294967295
        },
        "EntriesList": {
          "type": "list",
          "value": [
            {
              "__struct_id": 0,
              "Active": {
                "type": "resref",
                "value": ""
              },
              "Index": {
                "type": "dword",
                "value": 1
              },
              "IsChild": {
                "type": "byte",
                "value": 0
              }
            }
          ]
        },
        "Quest": {
          "type": "cexostring",
          "value": ""
        },
        "Script": {
          "type": "resref",
          "value": ""
        },
        "Sound": {
          "type": "resref",
          "value": ""
        },
        "Text": {
          "id": 32018,
          "type": "cexolocstring",
          "value": {}
        }
      },
      {
        "__struct_id": 4,
        "Animation": {
          "type": "dword",
          "value": 0
        },
        "AnimLoop": {
          "type": "byte",
          "value": 1
        },
        "Comment": {
          "type": "cexostring",
          "value": ""
        },
        "Delay": {
          "type": "dword",
          "value": 4294967295
        },
        "EntriesList": {
          "type": "list",
          "value": [
            {
              "__struct_id": 0,
              "Active": {
                "type": "resref",
                "value": ""
              },
              "Index": {
                "type": "dword",
                "value": 2
              },
              "IsChild": {
                "type": "byte",
                "value": 0
              }
            }
          ]
        },
        "Quest": {
          "type": "cexostring",
          "value": ""
        },
        "Script": {
          "type": "resref",
          "value": ""
        },
        "Sound": {
          "type": "resref",
          "value": ""
        },
        "Text": {
          "id": 32017,
          "type": "cexolocstring",
          "value": {}
        }
      },
      {
        "__struct_id": 5,
        "Animation": {
          "type": "dword",
          "value": 0
        },
        "AnimLoop": {
          "type": "byte",
          "value": 1
        },
        "Comment": {
          "type": "cexostring",
          "value": ""
        },
        "Delay": {
          "type": "dword",
          "value": 4294967295
        },
        "EntriesList": {
          "type": "list",
          "value": [
            {
              "__struct_id": 0,
              "Active": {
                "type": "resref",
                "value": ""
              },
              "Index": {
                "type": "dword",
                "value": 3
              },
              "IsChild": {
                "type": "byte",
                "value": 0
              }
            }
          ]
        },
        "Quest": {
          "type": "cexostring",
          "value": ""
        },
        "Script": {
          "type": "resref",
          "value": ""
        },
        "Sound": {
          "type": "resref",
          "value": ""
        },
        "Text": {
          "type": "cexolocstring",
          "value": {}
        }
      },
      {
        "__struct_id": 6,
        "Animation": {
          "type": "dword",
          "value": 0
        },
        "AnimLoop": {
          "type": "byte",
          "value": 1
        },
        "Comment": {
          "type": "cexostring",
          "value": ""
        },
        "Delay": {
          "type": "dword",
          "value": 4294967295
        },
        "EntriesList": {
          "type": "list",
          "value": [
            {
              "__struct_id": 0,
              "Active": {
                "type": "resref",
                "value": ""
              },
              "Index": {
                "type": "dword",
                "value": 1
              },
              "IsChild": {
                "type": "byte",
                "value": 1
              },
              "LinkComment": {
                "type": "cexostring",
                "value": ""
              }
            }
          ]
        },
        "Quest": {
          "type": "cexostring",
          "value": ""
        },
        "Script": {
          "type": "resref",
          "value": ""
        },
        "Sound": {
          "type": "resref",
          "value": ""
        },
        "Text": {
          "id": 32027,
          "type": "cexolocstring",
          "value": {}
        }
      },
      {
        "__struct_id": 7,
        "Animation": {
          "type": "dword",
          "value": 0
        },
        "AnimLoop": {
          "type": "byte",
          "value": 1
        },
        "Comment": {
          "type": "cexostring",
          "value": ""
        },
        "Delay": {
          "type": "dword",
          "value": 4294967295
        },
        "EntriesList": {
          "type": "list",
          "value": [
            {
              "__struct_id": 0,
              "Active": {
                "type": "resref",
                "value": ""
              },
              "Index": {
                "type": "dword",
                "value": 4
              },
              "IsChild": {
                "type": "byte",
                "value": 1
              },
              "LinkComment": {
                "type": "cexostring",
                "value": ""
              }
            }
          ]
        },
        "Quest": {
          "type": "cexostring",
          "value": ""
        },
        "Script": {
          "type": "resref",
          "value": ""
        },
        "Sound": {
          "type": "resref",
          "value": ""
        },
        "Text": {
          "id": 32026,
          "type": "cexolocstring",
          "value": {}
        }
      },
      {
        "__struct_id": 8,
        "Animation": {
          "type": "dword",
          "value": 0
        },
        "AnimLoop": {
          "type": "byte",
          "value": 1
        },
        "Comment": {
          "type": "cexostring",
          "value": ""
        },
        "Delay": {
          "type": "dword",
          "value": 4294967295
        },
        "EntriesList": {
          "type": "list",
          "value": [
            {
              "__struct_id": 0,
              "Active": {
                "type": "resref",
                "value": ""
              },
              "Index": {
                "type": "dword",
                "value": 4
              },
              "IsChild": {
                "type": "byte",
                "value": 1
              },
              "LinkComment": {
                "type": "cexostring",
                "value": ""
              }
            }
          ]
        },
        "Quest": {
          "type": "cexostring",
          "value": ""
        },
        "Script": {
          "type": "resref",
          "value": ""
        },
        "Sound": {
          "type": "resref",
          "value": ""
        },
        "Text": {
          "id": 32025,
          "type": "cexolocstring",
          "value": {}
        }
      },
      {
        "__struct_id": 9,
        "Animation": {
          "type": "dword",
          "value": 0
        },
        "AnimLoop": {
          "type": "byte",
          "value": 1
        },
        "Comment": {
          "type": "cexostring",
          "value": ""
        },
        "Delay": {
          "type": "dword",
          "value": 4294967295
        },
        "EntriesList": {
          "type": "list",
          "value": [
            {
              "__struct_id": 0,
              "Active": {
                "type": "resref",
                "value": ""
              },
              "Index": {
                "type": "dword",
                "value": 1
              },
              "IsChild": {
                "type": "byte",
                "value": 1
              },
              "LinkComment": {
                "type": "cexostring",
                "value": ""
              }
            }
          ]
        },
        "Quest": {
          "type": "cexostring",
          "value": ""
        },
        "Script": {
          "type": "resref",
          "value": ""
        },
        "Sound": {
          "type": "resref",
          "value": ""
        },
        "Text": {
          "id": 32024,
          "type": "cexolocstring",
          "value": {}
        }
      },
      {
        "__struct_id": 10,
        "Animation": {
          "type": "dword",
          "value": 0
        },
        "AnimLoop": {
          "type": "byte",
          "value": 1
        },
        "Comment": {
          "type": "cexostring",
          "value": ""
        },
        "Delay": {
          "type": "dword",
          "value": 4294967295
        },
        "EntriesList": {
          "type": "list",
          "value": [
            {
              "__struct_id": 0,
              "Active": {
                "type": "resref",
                "value": ""
              },
              "Index": {
                "type": "dword",
                "value": 4
              },
              "IsChild": {
                "type": "byte",
                "value": 1
              },
              "LinkComment": {
                "type": "cexostring",
                "value": ""
              }
            }
          ]
        },
        "Quest": {
          "type": "cexostring",
          "value": ""
        },
        "Script": {
          "type": "resref",
          "value": ""
        },
        "Sound": {
          "type": "resref",
          "value": ""
        },
        "Text": {
          "id": 32023,
          "type": "cexolocstring",
          "value": {}
        }
      },
      {
        "__struct_id": 11,
        "Animation": {
          "type": "dword",
          "value": 0
        },
        "AnimLoop": {
          "type": "byte",
          "value": 1
        },
        "Comment": {
          "type": "cexostring",
          "value": ""
        },
        "Delay": {
          "type": "dword",
          "value": 4294967295
        },
        "EntriesList": {
          "type": "list",
          "value": [
            {
              "__struct_id": 0,
              "Active": {
                "type": "resref",
                "value": ""
              },
              "Index": {
                "type": "dword",
                "value": 4
              },
              "IsChild": {
                "type": "byte",
                "value": 0
              }
            }
          ]
        },
        "Quest": {
          "type": "cexostring",
          "value": ""
        },
        "Script": {
          "type": "resref",
          "value": ""
        },
        "Sound": {
          "type": "resref",
          "value": ""
        },
        "Text": {
          "id": 32022,
          "type": "cexolocstring",
          "value": {}
        }
      },
      {
        "__struct_id": 12,
        "Animation": {
          "type": "dword",
          "value": 0
        },
        "AnimLoop": {
          "type": "byte",
          "value": 1
        },
        "Comment": {
          "type": "cexostring",
          "value": ""
        },
        "Delay": {
          "type": "dword",
          "value": 4294967295
        },
        "EntriesList": {
          "type": "list",
          "value": [
            {
              "__struct_id": 0,
              "Active": {
                "type": "resref",
                "value": ""
              },
              "Index": {
                "type": "dword",
                "value": 5
              },
              "IsChild": {
                "type": "byte",
                "value": 0
              }
            }
          ]
        },
        "Quest": {
          "type": "cexostring",
          "value": ""
        },
        "Script": {
          "type": "resref",
          "value": ""
        },
        "Sound": {
          "type": "resref",
          "value": ""
        },
        "Text": {
          "type": "cexolocstring",
          "value": {}
        }
      },
      {
        "__struct_id": 13,
        "Animation": {
          "type": "dword",
          "value": 0
        },
        "AnimLoop": {
          "type": "byte",
          "value": 1
        },
        "Comment": {
          "type": "cexostring",
          "value": ""
        },
        "Delay": {
          "type": "dword",
          "value": 4294967295
        },
        "EntriesList": {
          "type": "list",
          "value": [
            {
              "__struct_id": 0,
              "Active": {
                "type": "resref",
                "value": ""
              },
              "Index": {
                "type": "dword",
                "value": 1
              },
              "IsChild": {
                "type": "byte",
                "value": 1
              },
              "LinkComment": {
                "type": "cexostring",
                "value": ""
              }
            }
          ]
        },
        "Quest": {
          "type": "cexostring",
          "value": ""
        },
        "Script": {
          "type": "resref",
          "value": ""
        },
        "Sound": {
          "type": "resref",
          "value": ""
        },
        "Text": {
          "id": 32035,
          "type": "cexolocstring",
          "value": {}
        }
      },
      {
        "__struct_id": 14,
        "Animation": {
          "type": "dword",
          "value": 0
        },
        "AnimLoop": {
          "type": "byte",
          "value": 1
        },
        "Comment": {
          "type": "cexostring",
          "value": ""
        },
        "Delay": {
          "type": "dword",
          "value": 4294967295
        },
        "EntriesList": {
          "type": "list",
          "value": [
            {
              "__struct_id": 0,
              "Active": {
                "type": "resref",
                "value": ""
              },
              "Index": {
                "type": "dword",
                "value": 6
              },
              "IsChild": {
                "type": "byte",
                "value": 1
              },
              "LinkComment": {
                "type": "cexostring",
                "value": ""
              }
            }
          ]
        },
        "Quest": {
          "type": "cexostring",
          "value": ""
        },
        "Script": {
          "type": "resref",
          "value": ""
        },
        "Sound": {
          "type": "resref",
          "value": ""
        },
        "Text": {
          "id": 32034,
          "type": "cexolocstring",
          "value": {}
        }
      },
      {
        "__struct_id": 15,
        "Animation": {
          "type": "dword",
          "value": 0
        },
        "AnimLoop": {
          "type": "byte",
          "value": 1
        },
        "Comment": {
          "type": "cexostring",
          "value": ""
        },
        "Delay": {
          "type": "dword",
          "value": 4294967295
        },
        "EntriesList": {
          "type": "list",
          "value": [
            {
              "__struct_id": 0,
              "Active": {
                "type": "resref",
                "value": ""
              },
              "Index": {
                "type": "dword",
                "value": 7
              },
              "IsChild": {
                "type": "byte",
                "value": 1
              },
              "LinkComment": {
                "type": "cexostring",
                "value": ""
              }
            }
          ]
        },
        "Quest": {
          "type": "cexostring",
          "value": ""
        },
        "Script": {
          "type": "resref",
          "value": ""
        },
        "Sound": {
          "type": "resref",
          "value": ""
        },
        "Text": {
          "id": 32033,
          "type": "cexolocstring",
          "value": {}
        }
      },
      {
        "__struct_id": 16,
        "Animation": {
          "type": "dword",
          "value": 0
        },
        "AnimLoop": {
          "type": "byte",
          "value": 1
        },
        "Comment": {
          "type": "cexostring",
          "value": ""
        },
        "Delay": {
          "type": "dword",
          "value": 4294967295
        },
        "EntriesList": {
          "type": "list",
          "value": [
            {
              "__struct_id": 0,
              "Active": {
                "type": "resref",
                "value": ""
              },
              "Index": {
                "type": "dword",
                "value": 8
              },
              "IsChild": {
                "type": "byte",
                "value": 1
              },
              "LinkComment": {
                "type": "cexostring",
                "value": ""
              }
            }
          ]
        },
        "Quest": {
          "type": "cexostring",
          "value": ""
        },
        "Script": {
          "type": "resref",
          "value": ""
        },
        "Sound": {
          "type": "resref",
          "value": ""
        },
        "Text": {
          "id": 32032,
          "type": "cexolocstring",
          "value": {}
        }
      },
      {
        "__struct_id": 17,
        "Animation": {
          "type": "dword",
          "value": 0
        },
        "AnimLoop": {
          "type": "byte",
          "value": 1
        },
        "Comment": {
          "type": "cexostring",
          "value": ""
        },
        "Delay": {
          "type": "dword",
          "value": 4294967295
        },
        "EntriesList": {
          "type": "list",
          "value": [
            {
              "__struct_id": 0,
              "Active": {
                "type": "resref",
                "value": ""
              },
              "Index": {
                "type": "dword",
                "value": 1
              },
              "IsChild": {
                "type": "byte",
                "value": 1
              },
              "LinkComment": {
                "type": "cexostring",
                "value": ""
              }
            }
          ]
        },
        "Quest": {
          "type": "cexostring",
          "value": ""
        },
        "Script": {
          "type": "resref",
          "value": ""
        },
        "Sound": {
          "type": "resref",
          "value": ""
        },
        "Text": {
          "id": 32031,
          "type": "cexolocstring",
          "value": {}
        }
      },
      {
        "__struct_id": 18,
        "Animation": {
          "type": "dword",
          "value": 0
        },
        "AnimLoop": {
          "type": "byte",
          "value": 1
        },
        "Comment": {
          "type": "cexostring",
          "value": ""
        },
        "Delay": {
          "type": "dword",
          "value": 4294967295
        },
        "EntriesList": {
          "type": "list",
          "value": [
            {
              "__struct_id": 0,
              "Active": {
                "type": "resref",
                "value": ""
              },
              "Index": {
                "type": "dword",
                "value": 6
              },
              "IsChild": {
                "type": "byte",
                "value": 0
              }
            }
          ]
        },
        "Quest": {
          "type": "cexostring",
          "value": ""
        },
        "Script": {
          "type": "resref",
          "value": ""
        },
        "Sound": {
          "type": "resref",
          "value": ""
        },
        "Text": {
          "id": 32030,
          "type": "cexolocstring",
          "value": {}
        }
      },
      {
        "__struct_id": 19,
        "Animation": {
          "type": "dword",
          "value": 0
        },
        "AnimLoop": {
          "type": "byte",
          "value": 1
        },
        "Comment": {
          "type": "cexostring",
          "value": ""
        },
        "Delay": {
          "type": "dword",
          "value": 4294967295
        },
        "EntriesList": {
          "type": "list",
          "value": [
            {
              "__struct_id": 0,
              "Active": {
                "type": "resref",
                "value": ""
              },
              "Index": {
                "type": "dword",
                "value": 7
              },
              "IsChild": {
                "type": "byte",
                "value": 0
              }
            }
          ]
        },
        "Quest": {
          "type": "cexostring",
          "value": ""
        },
        "Script": {
          "type": "resref",
          "value": ""
        },
        "Sound": {
          "type": "resref",
          "value": ""
        },
        "Text": {
          "id": 32029,
          "type": "cexolocstring",
          "value": {}
        }
      },
      {
        "__struct_id": 20,
        "Animation": {
          "type": "dword",
          "value": 0
        },
        "AnimLoop": {
          "type": "byte",
          "value": 1
        },
        "Comment": {
          "type": "cexostring",
          "value": ""
        },
        "Delay": {
          "type": "dword",
          "value": 4294967295
        },
        "EntriesList": {
          "type": "list",
          "value": [
            {
              "__struct_id": 0,
              "Active": {
                "type": "resref",
                "value": ""
              },
              "Index": {
                "type": "dword",
                "value": 8
              },
              "IsChild": {
                "type": "byte",
                "value": 0
              }
            }
          ]
        },
        "Quest": {
          "type": "cexostring",
          "value": ""
        },
        "Script": {
          "type": "resref",
          "value": ""
        },
        "Sound": {
          "type": "resref",
          "value": ""
        },
        "Text": {
          "id": 32028,
          "type": "cexolocstring",
          "value": {}
        }
      },
      {
        "__struct_id": 21,
        "Animation": {
          "type": "dword",
          "value": 0
        },
        "AnimLoop": {
          "type": "byte",
          "value": 1
        },
        "Comment": {
          "type": "cexostring",
          "value": ""
        },
        "Delay": {
          "type": "dword",
          "value": 4294967295
        },
        "EntriesList": {
          "type": "list",
          "value": [
            {
              "__struct_id": 0,
              "Active": {
                "type": "resref",
                "value": ""
              },
              "Index": {
                "type": "dword",
                "value": 9
              },
              "IsChild": {
                "type": "byte",
                "value": 1
              },
              "LinkComment": {
                "type": "cexostring",
                "value": ""
              }
            }
          ]
        },
        "Quest": {
          "type": "cexostring",
          "value": ""
        },
        "Script": {
          "type": "resref",
          "value": ""
        },
        "Sound": {
          "type": "resref",
          "value": ""
        },
        "Text": {
          "id": 32045,
          "type": "cexolocstring",
          "value": {}
        }
      },
      {
        "__struct_id": 22,
        "Animation": {
          "type": "dword",
          "value": 0
        },
        "AnimLoop": {
          "type": "byte",
          "value": 1
        },
        "Comment": {
          "type": "cexostring",
          "value": ""
        },
        "Delay": {
          "type": "dword",
          "value": 4294967295
        },
        "EntriesList": {
          "type": "list",
          "value": [
            {
              "__struct_id": 0,
              "Active": {
                "type": "resref",
                "value": ""
              },
              "Index": {
                "type": "dword",
                "value": 9
              },
              "IsChild": {
                "type": "byte",
                "value": 0
              }
            }
          ]
        },
        "Quest": {
          "type": "cexostring",
          "value": ""
        },
        "Script": {
          "type": "resref",
          "value": ""
        },
        "Sound": {
          "type": "resref",
          "value": ""
        },
        "Text": {
          "id": 32044,
          "type": "cexolocstring",
          "value": {}
        }
      },
      {
        "__struct_id": 23,
        "Animation": {
          "type": "dword",
          "value": 0
        },
        "AnimLoop": {
          "type": "byte",
          "value": 1
        },
        "Comment": {
          "type": "cexostring",
          "value": ""
        },
        "Delay": {
          "type": "dword",
          "value": 4294967295
        },
        "EntriesList": {
          "type": "list",
          "value": [
            {
              "__struct_id": 0,
              "Active": {
                "type": "resref",
                "value": ""
              },
              "Index": {
                "type": "dword",
                "value": 10
              },
              "IsChild": {
                "type": "byte",
                "value": 1
              },
              "LinkComment": {
                "type": "cexostring",
                "value": ""
              }
            }
          ]
        },
        "Quest": {
          "type": "cexostring",
          "value": ""
        },
        "Script": {
          "type": "resref",
          "value": ""
        },
        "Sound": {
          "type": "resref",
          "value": ""
        },
        "Text": {
          "id": 32043,
          "type": "cexolocstring",
          "value": {}
        }
      },
      {
        "__struct_id": 24,
        "Animation": {
          "type": "dword",
          "value": 0
        },
        "AnimLoop": {
          "type": "byte",
          "value": 1
        },
        "Comment": {
          "type": "cexostring",
          "value": ""
        },
        "Delay": {
          "type": "dword",
          "value": 4294967295
        },
        "EntriesList": {
          "type": "list",
          "value": [
            {
              "__struct_id": 0,
              "Active": {
                "type": "resref",
                "value": ""
              },
              "Index": {
                "type": "dword",
                "value": 10
              },
              "IsChild": {
                "type": "byte",
                "value": 0
              }
            }
          ]
        },
        "Quest": {
          "type": "cexostring",
          "value": ""
        },
        "Script": {
          "type": "resref",
          "value": ""
        },
        "Sound": {
          "type": "resref",
          "value": ""
        },
        "Text": {
          "id": 32042,
          "type": "cexolocstring",
          "value": {}
        }
      },
      {
        "__struct_id": 25,
        "Animation": {
          "type": "dword",
          "value": 0
        },
        "AnimLoop": {
          "type": "byte",
          "value": 1
        },
        "Comment": {
          "type": "cexostring",
          "value": ""
        },
        "Delay": {
          "type": "dword",
          "value": 4294967295
        },
        "EntriesList": {
          "type": "list",
          "value": [
            {
              "__struct_id": 0,
              "Active": {
                "type": "resref",
                "value": ""
              },
              "Index": {
                "type": "dword",
                "value": 11
              },
              "IsChild": {
                "type": "byte",
                "value": 0
              }
            }
          ]
        },
        "Quest": {
          "type": "cexostring",
          "value": ""
        },
        "Script": {
          "type": "resref",
          "value": ""
        },
        "Sound": {
          "type": "resref",
          "value": ""
        },
        "Text": {
          "id": 32016,
          "type": "cexolocstring",
          "value": {}
        }
      },
      {
        "__struct_id": 26,
        "Animation": {
          "type": "dword",
          "value": 0
        },
        "AnimLoop": {
          "type": "byte",
          "value": 1
        },
        "Comment": {
          "type": "cexostring",
          "value": ""
        },
        "Delay": {
          "type": "dword",
          "value": 4294967295
        },
        "EntriesList": {
          "type": "list",
          "value": [
            {
              "__struct_id": 0,
              "Active": {
                "type": "resref",
                "value": ""
              },
              "Index": {
                "type": "dword",
                "value": 2
              },
              "IsChild": {
                "type": "byte",
                "value": 1
              },
              "LinkComment": {
                "type": "cexostring",
                "value": ""
              }
            }
          ]
        },
        "Quest": {
          "type": "cexostring",
          "value": ""
        },
        "Script": {
          "type": "resref",
          "value": ""
        },
        "Sound": {
          "type": "resref",
          "value": ""
        },
        "Text": {
          "type": "cexolocstring",
          "value": {}
        }
      },
      {
        "__struct_id": 27,
        "Animation": {
          "type": "dword",
          "value": 0
        },
        "AnimLoop": {
          "type": "byte",
          "value": 1
        },
        "Comment": {
          "type": "cexostring",
          "value": ""
        },
        "Delay": {
          "type": "dword",
          "value": 4294967295
        },
        "EntriesList": {
          "type": "list",
          "value": [
            {
              "__struct_id": 0,
              "Active": {
                "type": "resref",
                "value": ""
              },
              "Index": {
                "type": "dword",
                "value": 1
              },
              "IsChild": {
                "type": "byte",
                "value": 1
              },
              "LinkComment": {
                "type": "cexostring",
                "value": ""
              }
            }
          ]
        },
        "Quest": {
          "type": "cexostring",
          "value": ""
        },
        "Script": {
          "type": "resref",
          "value": ""
        },
        "Sound": {
          "type": "resref",
          "value": ""
        },
        "Text": {
          "id": 32041,
          "type": "cexolocstring",
          "value": {}
        }
      },
      {
        "__struct_id": 28,
        "Animation": {
          "type": "dword",
          "value": 0
        },
        "AnimLoop": {
          "type": "byte",
          "value": 1
        },
        "Comment": {
          "type": "cexostring",
          "value": ""
        },
        "Delay": {
          "type": "dword",
          "value": 4294967295
        },
        "EntriesList": {
          "type": "list",
          "value": [
            {
              "__struct_id": 0,
              "Active": {
                "type": "resref",
                "value": ""
              },
              "Index": {
                "type": "dword",
                "value": 7
              },
              "IsChild": {
                "type": "byte",
                "value": 1
              },
              "LinkComment": {
                "type": "cexostring",
                "value": ""
              }
            }
          ]
        },
        "Quest": {
          "type": "cexostring",
          "value": ""
        },
        "Script": {
          "type": "resref",
          "value": ""
        },
        "Sound": {
          "type": "resref",
          "value": ""
        },
        "Text": {
          "id": 32040,
          "type": "cexolocstring",
          "value": {}
        }
      },
      {
        "__struct_id": 29,
        "Animation": {
          "type": "dword",
          "value": 0
        },
        "AnimLoop": {
          "type": "byte",
          "value": 1
        },
        "Comment": {
          "type": "cexostring",
          "value": ""
        },
        "Delay": {
          "type": "dword",
          "value": 4294967295
        },
        "EntriesList": {
          "type": "list",
          "value": [
            {
              "__struct_id": 0,
              "Active": {
                "type": "resref",
                "value": ""
              },
              "Index": {
                "type": "dword",
                "value": 2
              },
              "IsChild": {
                "type": "byte",
                "value": 1
              },
              "LinkComment": {
                "type": "cexostring",
                "value": ""
              }
            }
          ]
        },
        "Quest": {
          "type": "cexostring",
          "value": ""
        },
        "Script": {
          "type": "resref",
          "value": ""
        },
        "Sound": {
          "type": "resref",
          "value": ""
        },
        "Text": {
          "id": 32039,
          "type": "cexolocstring",
          "value": {}
        }
      },
      {
        "__struct_id": 30,
        "Animation": {
          "type": "dword",
          "value": 0
        },
        "AnimLoop": {
          "type": "byte",
          "value": 1
        },
        "Comment": {
          "type": "cexostring",
          "value": ""
        },
        "Delay": {
          "type": "dword",
          "value": 4294967295
        },
        "EntriesList": {
          "type": "list",
          "value": [
            {
              "__struct_id": 0,
              "Active": {
                "type": "resref",
                "value": ""
              },
              "Index": {
                "type": "dword",
                "value": 1
              },
              "IsChild": {
                "type": "byte",
                "value": 1
              },
              "LinkComment": {
                "type": "cexostring",
                "value": ""
              }
            }
          ]
        },
        "Quest": {
          "type": "cexostring",
          "value": ""
        },
        "Script": {
          "type": "resref",
          "value": ""
        },
        "Sound": {
          "type": "resref",
          "value": ""
        },
        "Text": {
          "id": 32038,
          "type": "cexolocstring",
          "value": {}
        }
      },
      {
        "__struct_id": 31,
        "Animation": {
          "type": "dword",
          "value": 0
        },
        "AnimLoop": {
          "type": "byte",
          "value": 1
        },
        "Comment": {
          "type": "cexostring",
          "value": ""
        },
        "Delay": {
          "type": "dword",
          "value": 4294967295
        },
        "EntriesList": {
          "type": "list",
          "value": [
            {
              "__struct_id": 0,
              "Active": {
                "type": "resref",
                "value": ""
              },
              "Index": {
                "type": "dword",
                "value": 7
              },
              "IsChild": {
                "type": "byte",
                "value": 1
              },
              "LinkComment": {
                "type": "cexostring",
                "value": ""
              }
            }
          ]
        },
        "Quest": {
          "type": "cexostring",
          "value": ""
        },
        "Script": {
          "type": "resref",
          "value": ""
        },
        "Sound": {
          "type": "resref",
          "value": ""
        },
        "Text": {
          "id": 32037,
          "type": "cexolocstring",
          "value": {}
        }
      },
      {
        "__struct_id": 32,
        "Animation": {
          "type": "dword",
          "value": 0
        },
        "AnimLoop": {
          "type": "byte",
          "value": 1
        },
        "Comment": {
          "type": "cexostring",
          "value": ""
        },
        "Delay": {
          "type": "dword",
          "value": 4294967295
        },
        "EntriesList": {
          "type": "list",
          "value": [
            {
              "__struct_id": 0,
              "Active": {
                "type": "resref",
                "value": ""
              },
              "Index": {
                "type": "dword",
                "value": 2
              },
              "IsChild": {
                "type": "byte",
                "value": 1
              },
              "LinkComment": {
                "type": "cexostring",
                "value": ""
              }
            }
          ]
        },
        "Quest": {
          "type": "cexostring",
          "value": ""
        },
        "Script": {
          "type": "resref",
          "value": ""
        },
        "Sound": {
          "type": "resref",
          "value": ""
        },
        "Text": {
          "id": 32036,
          "type": "cexolocstring",
          "value": {}
        }
      },
      {
        "__struct_id": 33,
        "Animation": {
          "type": "dword",
          "value": 0
        },
        "AnimLoop": {
          "type": "byte",
          "value": 1
        },
        "Comment": {
          "type": "cexostring",
          "value": ""
        },
        "Delay": {
          "type": "dword",
          "value": 4294967295
        },
        "EntriesList": {
          "type": "list",
          "value": [
            {
              "__struct_id": 0,
              "Active": {
                "type": "resref",
                "value": ""
              },
              "Index": {
                "type": "dword",
                "value": 14
              },
              "IsChild": {
                "type": "byte",
                "value": 0
              }
            }
          ]
        },
        "Quest": {
          "type": "cexostring",
          "value": ""
        },
        "Script": {
          "type": "resref",
          "value": ""
        },
        "Sound": {
          "type": "resref",
          "value": ""
        },
        "Text": {
          "id": 68100,
          "type": "cexolocstring",
          "value": {}
        }
      },
      {
        "__struct_id": 34,
        "Animation": {
          "type": "dword",
          "value": 0
        },
        "AnimLoop": {
          "type": "byte",
          "value": 1
        },
        "Comment": {
          "type": "cexostring",
          "value": ""
        },
        "Delay": {
          "type": "dword",
          "value": 4294967295
        },
        "EntriesList": {
          "type": "list",
          "value": [
            {
              "__struct_id": 0,
              "Active": {
                "type": "resref",
                "value": ""
              },
              "Index": {
                "type": "dword",
                "value": 16
              },
              "IsChild": {
                "type": "byte",
                "value": 0
              }
            }
          ]
        },
        "Quest": {
          "type": "cexostring",
          "value": ""
        },
        "Script": {
          "type": "resref",
          "value": ""
        },
        "Sound": {
          "type": "resref",
          "value": ""
        },
        "Text": {
          "id": 68101,
          "type": "cexolocstring",
          "value": {}
        }
      }
    ]
  },
  "StartingList": {
    "type": "list",
    "value": [
      {
        "__struct_id": 0,
        "Active": {
          "type": "resref",
          "value": "m2q1ascbal3"
        },
        "Index": {
          "type": "dword",
          "value": 15
        }
      },
      {
        "__struct_id": 1,
        "Active": {
          "type": "resref",
          "value": "m2q1ascbal2"
        },
        "Index": {
          "type": "dword",
          "value": 13
        }
      },
      {
        "__struct_id": 2,
        "Active": {
          "type": "resref",
          "value": "m2q1ascbal1"
        },
        "Index": {
          "type": "dword",
          "value": 12
        }
      },
      {
        "__struct_id": 3,
        "Active": {
          "type": "resref",
          "value": ""
        },
        "Index": {
          "type": "dword",
          "value": 0
        }
      }
    ]
  }
}
